Workbook

Sheet INTRODUCCION
B1: PROCESO
B2: 1. VAMOS A CALCULAR LA LEY BENFORD CON UNO, DOS Y LOS DOS PRIMEROS DIGITOS
B3: 2. LUEGO VAMOS A CALCULAR LA DESVIACION ABSOLUTA MEDIA
B4: 3. VAMOS A CALCULAR EL CHI CUADRADO Y LO VAMOS A COMPARAR CON EL VALOR DEL CHI CUADRADO CRITICO
B5: DE ACUERDO AL RESULTADO VAMOS A INDICAR SI LOS DATOS SON FIABLES O NO
B7: EN LAS SIGUIENTES HOJAS ESTAN LOS EJEMPLO DE CADA UNO DE ESTOS CASOS
B9: TODO PARTE DE UN MOVIMIENTO CONTABLE REAL QUE ESTA EN LA HOJA MOVIMIENTO
B11: VAMOS A HACER ESTA PRUEBA CON EL DATO VALOR QUE ESTA EN LA COLUMNA J
B13: TAMBIEN ES IMPORTANTE VER QUE TENEMOS 9.656 REGISTROS
B15: TENGAMOS EN CUENTA QUE CUANDO EL VALOR ES CERO
B16: PARA EL PRIMER, SEGUNDO Y DOS PRIMEROS VALORES TOME 0
B17: TAMBIEN CUANDO ES SOLO DE UN DIGITO, POR EJEMPLO 1 , ENTONCES PARA EL SEGUNDO VALOR Y LOS DOS PRIMEROS TOME 0

Sheet MOVIMIENTO
A1: REGISTRO | B1: CUENTA | C1: COMPROBANTE | D1: FECHA | E1: DOCUMENTO | F1: DOCUMENTO_REFERENCIA | G1: NIT | H1: DETALLE | I1: TIPO | J1: VALOR | K1: VALOR_BASE | L1: CENTRO_DE_COSTOS | M1: TRANSACCIÓN_BANCO | N1: PLAZO
A2: 1 | B2: 11050503 | C2: 23 | D2: 42736 | E2: 1 | F2: 1 | H2: CUADRE DE ITAG?? | I2: 2 | J2: 153800 | K2: 0 | N2: 0
A3: =+A2+1 -> 2 | B3: 28109500 | C3: 23 | D3: 42736 | E3: 1 | F3: 1 | G3: 1 | H3: CUADRE DE ITAG?? | I3: 2 | J3: 9000 | K3: 0 | N3: 0
A4: =+A3+1 -> 3 | B4: 11100502 | C4: 23 | D4: 42736 | E4: 1 | F4: 8521 | H4: CUADRE DE ITAG?? | I4: 1 | J4: 37800 | K4: 0 | N4: 0
A5: =+A4+1 -> 4 | B5: 11100504 | C5: 23 | D5: 42736 | E5: 1 | F5: 1 | H5: CUADRE DE ITAG?? | I5: 1 | J5: 100000 | K5: 0 | N5: 0
A6: =+A5+1 -> 5 | B6: 52359520 | C6: 23 | D6: 42736 | E6: 1 | F6: 2935 | G6: 71336216 | H6: CUADRE DE ITAG?? | I6: 1 | J6: 25000 | K6: 0 | L6: 4 | N6: 0
A7: =+A6+1 -> 6 | B7: 11050503 | C7: 23 | D7: 42767 | E7: 1 | F7: 1 | H7: CUADRE DE ITAG?? | I7: 2 | J7: 182900 | K7: 0 | N7: 0
A8: =+A7+1 -> 7 | B8: 11100502 | C8: 23 | D8: 42767 | E8: 1 | F8: 8522 | H8: CUADRE DE ITAG?? | I8: 1 | J8: 157900 | K8: 0 | N8: 0
A9: =+A8+1 -> 8 | B9: 52359510 | C9: 23 | D9: 42767 | E9: 1 | F9: 2936 | G9: 71336216 | H9: CUADRE DE ITAG?? | I9: 1 | J9: 25000 | K9: 0 | L9: 4 | N9: 0
A10: =+A9+1 -> 9 | B10: 11050503 | C10: 23 | D10: 42795 | E10: 1 | F10: 1 | H10: CUADRE DE ITAG?? | I10: 2 | J10: 181550 | K10: 0 | N10: 0
A11: =+A10+1 -> 10 | B11: 529530 | C11: 23 | D11: 42795 | E11: 1 | F11: 1 | G11: 70517854 | H11: CUADRE DE ITAG?? | I11: 1 | J11: 6000 | K11: 0 | L11: 4 | N11: 0
A12: =+A11+1 -> 11 | B12: 23354000 | C12: 23 | D12: 42795 | E12: 1 | F12: 1 | G12: 6788222 | H12: CUADRE DE ITAG?? | I12: 1 | J12: 175550 | K12: 0 | N12: 0
A13: =+A12+1 -> 12 | B13: 11050503 | C13: 23 | D13: 42826 | E13: 1 | F13: 1 | H13: CUADRE DE ITAG?? | I13: 2 | J13: 75500 | K13: 0 | N13: 0
A14: =+A13+1 -> 13 | B14: 73959510 | C14: 23 | D14: 42826 | E14: 1 | F14: 1 | G14: 19336633 | H14: CUADRE DE ITAG?? | I14: 1 | J14: 1000 | K14: 0 | L14: 4 | N14: 0
A15: =+A14+1 -> 14 | B15: 23354000 | C15: 23 | D15: 42826 | E15: 1 | F15: 1 | G15: 6788222 | H15: CUADRE DE ITAG?? | I15: 1 | J15: 74500 | K15: 0 | N15: 0
A16: =+A15+1 -> 15 | B16: 11050503 | C16: 23 | D16: 42856 | E16: 1 | F16: 1 | H16: CUADRE DE ITAG?? | I16: 2 | J16: 184610 | K16: 0 | N16: 0
A17: =+A16+1 -> 16 | B17: 23354000 | C17: 23 | D17: 42856 | E17: 1 | F17: 1 | G17: 6788222 | H17: CUADRE DE ITAG?? | I17: 1 | J17: 184610 | K17: 0 | N17: 0
A18: =+A17+1 -> 17 | B18: 11050503 | C18: 23 | D18: 42887 | E18: 1 | F18: 1 | H18: CUADRE DE ITAG?? | I18: 2 | J18: 128000 | K18: 0 | N18: 0
A19: =+A18+1 -> 18 | B19: 23354000 | C19: 23 | D19: 42887 | E19: 1 | F19: 1 | G19: 6788222 | H19: CUADRE DE ITAG?? | I19: 1 | J19: 128000 | K19: 0 | N19: 0
A20: =+A19+1 -> 19 | B20: 11050503 | C20: 23 | D20: 42917 | E20: 1 | F20: 1 | H20: CUADRE DE ITAG?? | I20: 2 | J20: 370370 | K20: 0 | N20: 0
A21: =+A20+1 -> 20 | B21: 23354000 | C21: 23 | D21: 42917 | E21: 1 | F21: 1 | G21: 6788222 | H21: CUADRE DE ITAG?? | I21: 1 | J21: 324485 | K21: 0 | N21: 0
A22: =+A21+1 -> 21 | B22: 11100502 | C22: 23 | D22: 42917 | E22: 1 | F22: 8560 | H22: CUADRE DE ITAG?? | I22: 1 | J22: 45885 | K22: 0 | N22: 0
A23: =+A22+1 -> 22 | B23: 11050503 | C23: 23 | D23: 42948 | E23: 1 | F23: 1 | H23: CUADRE DE ITAG?? | I23: 2 | J23: 352295 | K23: 0 | N23: 0
A24: =+A23+1 -> 23 | B24: 11100507 | C24: 23 | D24: 42948 | E24: 1 | F24: 2581 | H24: CUADRE DE ITAG?? | I24: 1 | J24: 335095 | K24: 0 | N24: 0
A25: =+A24+1 -> 24 | B25: 73959510 | C25: 23 | D25: 42948 | E25: 1 | F25: 2938 | G25: 21397122 | H25: CUADRE DE ITAG?? | I25: 1 | J25: 1800 | K25: 0 | L25: 4 | N25: 0
A26: =+A25+1 -> 25 | B26: 523505 | C26: 23 | D26: 42948 | E26: 1 | F26: 2937 | G26: 70516226 | H26: CUADRE DE ITAG?? | I26: 1 | J26: 7000 | K26: 0 | L26: 4 | N26: 0
A27: =+A26+1 -> 26 | B27: 22059510 | C27: 23 | D27: 42948 | E27: 1 | F27: 12757 | G27: 860025900 | H27: CUADRE DE ITAG?? | I27: 1 | J27: 8375 | K27: 0 | N27: 0
A28: =+A27+1 -> 27 | B28: 53955300 | C28: 23 | D28: 42948 | E28: 1 | F28: 1 | G28: 3399878 | H28: CUADRE DE ITAG?? | I28: 1 | J28: 25 | K28: 0 | L28: 4 | N28: 0
A29: =+A28+1 -> 28 | B29: 11050503 | C29: 23 | D29: 42979 | E29: 1 | F29: 1 | H29: CUADRE DE ITAG?? | I29: 2 | J29: 182350 | K29: 0 | N29: 0
A30: =+A29+1 -> 29 | B30: 11100507 | C30: 23 | D30: 42979 | E30: 1 | F30: 2578 | H30: CUADRE DE ITAG?? | I30: 1 | J30: 157350 | K30: 0 | N30: 0
A31: =+A30+1 -> 30 | B31: 52359520 | C31: 23 | D31: 42979 | E31: 1 | F31: 2939 | G31: 71336216 | H31: CUADRE DE ITAG?? | I31: 1 | J31: 25000 | K31: 0 | L31: 4 | N31: 0
A32: =+A31+1 -> 31 | B32: 11050503 | C32: 23 | D32: 43009 | E32: 1 | F32: 1 | H32: CUADRE DE ITAG?? | I32: 2 | J32: 126600 | K32: 0 | N32: 0
A33: =+A32+1 -> 32 | B33: 11100507 | C33: 23 | D33: 43009 | E33: 1 | F33: 2579 | H33: CUADRE DE ITAG?? | I33: 1 | J33: 101600 | K33: 0 | N33: 0
A34: =+A33+1 -> 33 | B34: 52359520 | C34: 23 | D34: 43009 | E34: 1 | F34: 2940 | G34: 71336216 | H34: CUADRE DE ITAG?? | I34: 1 | J34: 25000 | K34: 0 | L34: 4 | N34: 0
A35: =+A34+1 -> 34 | B35: 11050504 | C35: 27 | D35: 42736 | E35: 1 | F35: 1 | H35: CUADRE COPACABANA | I35: 2 | J35: 153300 | K35: 0 | N35: 0
A36: =+A35+1 -> 35 | B36: 11100504 | C36: 27 | D36: 42736 | E36: 1 | F36: 1 | H36: CUADRE COPACABANA | I36: 1 | J36: 153300 | K36: 0 | N36: 0
A37: =+A36+1 -> 36 | B37: 11050504 | C37: 27 | D37: 42767 | E37: 1 | F37: 1 | H37: CUADRE COPACABANA | I37: 2 | J37: 217300 | K37: 0 | N37: 0
A38: =+A37+1 -> 37 | B38: 11100502 | C38: 27 | D38: 42767 | E38: 1 | F38: 8514 | H38: CUADRE COPACABANA | I38: 1 | J38: 217300 | K38: 0 | N38: 0
A39: =+A38+1 -> 38 | B39: 11050504 | C39: 27 | D39: 42795 | E39: 1 | F39: 1 | H39: CUADRE COPACABANA | I39: 2 | J39: 152200 | K39: 0 | N39: 0
A40: =+A39+1 -> 39 | B40: 11100507 | C40: 27 | D40: 42795 | E40: 1 | F40: 2576 | H40: CUADRE COPACABANA | I40: 1 | J40: 147900 | K40: 0 | N40: 0
A41: =+A40+1 -> 40 | B41: 529530 | C41: 27 | D41: 42795 | E41: 1 | F41: 7595 | G41: 15508569 | H41: CUADRE COPACABANA | I41: 1 | J41: 4300 | K41: 0 | L41: 5 | N41: 0
A42: =+A41+1 -> 41 | B42: 11050504 | C42: 27 | D42: 42826 | E42: 1 | F42: 1 | H42: CUADRE COPACABANA | I42: 2 | J42: 183100 | K42: 0 | N42: 0
A43: =+A42+1 -> 42 | B43: 11100507 | C43: 27 | D43: 42826 | E43: 1 | F43: 2575 | H43: CUADRE COPACABANA | I43: 1 | J43: 183100 | K43: 0 | N43: 0
A44: =+A43+1 -> 43 | B44: 11050504 | C44: 27 | D44: 42856 | E44: 1 | F44: 1 | H44: CUADRE COPACABANA | I44: 2 | J44: 257650 | K44: 0 | N44: 0
A45: =+A44+1 -> 44 | B45: 11100502 | C45: 27 | D45: 42856 | E45: 1 | F45: 8552 | H45: CUADRE COPACABANA | I45: 1 | J45: 257100 | K45: 0 | N45: 0
A46: =+A45+1 -> 45 | B46: 73959510 | C46: 27 | D46: 42856 | E46: 1 | F46: 3102 | G46: 6784448-1 | H46: CUADRE COPACABANA | I46: 1 | J46: 550 | K46: 0 | L46: 5 | N46: 0
A47: =+A46+1 -> 46 | B47: 11050504 | C47: 27 | D47: 42887 | E47: 1 | F47: 1 | H47: CUADRE COPACABANA | I47: 2 | J47: 214100 | K47: 0 | N47: 0
A48: =+A47+1 -> 47 | B48: 11100502 | C48: 27 | D48: 42887 | E48: 1 | F48: 8551 | H48: CUADRE COPACABANA | I48: 1 | J48: 214100 | K48: 0 | N48: 0
A49: =+A48+1 -> 48 | B49: 11050504 | C49: 27 | D49: 42917 | E49: 1 | F49: 1 | H49: CUADRE COPACABANA | I49: 2 | J49: 316315 | K49: 0 | N49: 0
A50: =+A49+1 -> 49 | B50: 11100502 | C50: 27 | D50: 42917 | E50: 1 | F50: 8550 | H50: CUADRE COPACABANA | I50: 1 | J50: 311565 | K50: 0 | N50: 0
A51: =+A50+1 -> 50 | B51: 73959510 | C51: 27 | D51: 42917 | E51: 1 | F51: 3103 | G51: 6784448-1 | H51: CUADRE COPACABANA | I51: 1 | J51: 4750 | K51: 0 | L51: 5 | N51: 0
A52: =+A51+1 -> 51 | B52: 11050501 | C52: 21 | D52: 42795 | E52: 1 | F52: 1 | H52: CUADRE FABRICA | I52: 2 | J52: 1338541 | K52: 0 | N52: 0
A53: =+A52+1 -> 52 | B53: 11100507 | C53: 21 | D53: 42795 | E53: 1 | F53: 6691 | H53: CUADRE FABRICA | I53: 1 | J53: 116633 | K53: 0 | N53: 0
A54: =+A53+1 -> 53 | B54: 11201010 | C54: 21 | D54: 42795 | E54: 1 | F54: 1 | H54: CUADRE FABRICA | I54: 1 | J54: 450000 | K54: 0 | N54: 0
A55: =+A54+1 -> 54 | B55: 11100502 | C55: 21 | D55: 42795 | E55: 1 | F55: 6714 | H55: CUADRE FABRICA | I55: 1 | J55: 673178 | K55: 0 | N55: 0
A56: =+A55+1 -> 55 | B56: 529535 | C56: 21 | D56: 42795 | E56: 1 | F56: 4124 | G56: 800222779 | H56: CUADRE FABRICA | I56: 1 | J56: 12000 | K56: 0 | L56: 1 | N56: 0
A57: =+A56+1 -> 56 | B57: 523550 | C57: 21 | D57: 42795 | E57: 1 | F57: 6197 | G57: 890700476 | H57: CUADRE FABRICA | I57: 1 | J57: 27000 | K57: 0 | L57: 1 | N57: 0
A58: =+A57+1 -> 57 | B58: 22059510 | C58: 21 | D58: 42795 | E58: 1 | F58: 12759 | G58: 811029831 | H58: CUADRE FABRICA | I58: 1 | J58: 43740 | K58: 0 | N58: 0
A59: =+A58+1 -> 58 | B59: 22059510 | C59: 21 | D59: 42795 | E59: 1 | F59: 12760 | G59: 800196314 | H59: CUADRE FABRICA | I59: 1 | J59: 15990 | K59: 0 | N59: 0
A60: =+A59+1 -> 59 | B60: 11050501 | C60: 21 | D60: 42826 | E60: 1 | F60: 1 | H60: CUADRE FABRICA | I60: 2 | J60: 3777849 | K60: 0 | N60: 0
A61: =+A60+1 -> 60 | B61: 11100507 | C61: 21 | D61: 42826 | E61: 1 | F61: 6689 | H61: CUADRE FABRICA | I61: 1 | J61: 841508 | K61: 0 | N61: 0
A62: =+A61+1 -> 61 | B62: 11100502 | C62: 21 | D62: 42826 | E62: 1 | F62: 8513 | H62: CUADRE FABRICA | I62: 1 | J62: 31750 | K62: 0 | N62: 0
A63: =+A62+1 -> 62 | B63: 11100502 | C63: 21 | D63: 42826 | E63: 1 | F63: 8528 | H63: CUADRE FABRICA | I63: 1 | J63: 398615 | K63: 0 | N63: 0
A64: =+A63+1 -> 63 | B64: 11100507 | C64: 21 | D64: 42826 | E64: 1 | F64: 2566 | H64: CUADRE FABRICA | I64: 1 | J64: 1508000 | K64: 0 | N64: 0
A65: =+A64+1 -> 64 | B65: 11050500 | C65: 21 | D65: 42826 | E65: 1 | F65: 1 | H65: CUADRE FABRICA CON/CON/DIC | I65: 1 | J65: 160817 | K65: 0 | N65: 0
A66: =+A65+1 -> 65 | B66: 11050500 | C66: 21 | D66: 42826 | E66: 1 | F66: 6108 | H66: CUADRE FABRICA CON/CO/DIC | I66: 1 | J66: 130100 | K66: 0 | N66: 0
A67: =+A66+1 -> 66 | B67: 11100504 | C67: 21 | D67: 42826 | E67: 1 | F67: 1 | H67: CUADRE FABRICA | I67: 1 | J67: 229432 | K67: 0 | N67: 0
A68: =+A67+1 -> 67 | B68: 529535 | C68: 21 | D68: 42826 | E68: 1 | F68: 9060 | G68: 70550521 | H68: CUADRE FABRICA | I68: 1 | J68: 40000 | K68: 0 | L68: 1 | N68: 0
A69: =+A68+1 -> 68 | B69: 524540 | C69: 21 | D69: 42826 | E69: 1 | F69: 1255 | G69: 890931835 | H69: CUADRE FABRICA | I69: 1 | J69: 33159 | K69: 0 | L69: 1 | N69: 0
A70: =+A69+1 -> 69 | B70: 529530 | C70: 21 | D70: 42826 | E70: 1 | F70: 1 | G70: 32300937 | H70: CUADRE FABRICA | I70: 1 | J70: 11600 | K70: 0 | L70: 1 | N70: 0
A71: =+A70+1 -> 70 | B71: 11050500 | C71: 21 | D71: 42826 | E71: 1 | F71: 7572 | H71: CUADRE FABRICA | I71: 1 | J71: 84480 | K71: 0 | N71: 0
A72: =+A71+1 -> 71 | B72: 11050500 | C72: 21 | D72: 42826 | E72: 1 | F72: 7573 | H72: CUADRE FABRICA | I72: 1 | J72: 167033 | K72: 0 | N72: 0
A73: =+A72+1 -> 72 | B73: 11050500 | C73: 21 | D73: 42826 | E73: 1 | F73: 7575 | H73: CUADRE FABRICA | I73: 1 | J73: 141355 | K73: 0 | N73: 0
A74: =+A73+1 -> 73 | B74: 11050501 | C74: 21 | D74: 42856 | E74: 1 | F74: 1 | H74: CUADRE FABRICA | I74: 2 | J74: 2211837 | K74: 0 | N74: 0
A75: =+A74+1 -> 74 | B75: 11100508 | C75: 21 | D75: 42856 | E75: 1 | F75: 7440 | H75: CUADRE FABRICA | I75: 1 | J75: 498641 | K75: 0 | N75: 0
A76: =+A75+1 -> 75 | B76: 11100502 | C76: 21 | D76: 42856 | E76: 1 | F76: 8562 | H76: CUADRE FABRICA | I76: 1 | J76: 106600 | K76: 0 | N76: 0
A77: =+A76+1 -> 76 | B77: 11201010 | C77: 21 | D77: 42856 | E77: 1 | F77: 8441 | H77: CUADRE FABRICA | I77: 1 | J77: 1292000 | K77: 0 | N77: 0
A78: =+A77+1 -> 77 | B78: 11201010 | C78: 21 | D78: 42856 | E78: 1 | F78: 8441 | H78: CUADRE FABRICA | I78: 1 | J78: 114000 | K78: 0 | N78: 0
A79: =+A78+1 -> 78 | B79: 529535 | C79: 21 | D79: 42856 | E79: 1 | F79: 1 | G79: 811030693 | H79: CUADRE FABRICA | I79: 1 | J79: 42393 | K79: 0 | L79: 1 | N79: 0
A80: =+A79+1 -> 79 | B80: 529535 | C80: 21 | D80: 42856 | E80: 1 | F80: 1 | G80: 16224899 | H80: CUADRE FABRICA | I80: 1 | J80: 38008 | K80: 0 | L80: 1 | N80: 0
A81: =+A80+1 -> 80 | B81: 73959510 | C81: 21 | D81: 42856 | E81: 1 | F81: 4050 | G81: 811029831 | H81: CUADRE FABRICA | I81: 1 | J81: 44190 | K81: 0 | L81: 1 | N81: 0
A82: =+A81+1 -> 81 | B82: 529560 | C82: 21 | D82: 42856 | E82: 1 | F82: 1 | G82: 8596565 | H82: CUADRE FABRICA | I82: 1 | J82: 10000 | K82: 0 | L82: 1 | N82: 0
A83: =+A82+1 -> 82 | B83: 529560 | C83: 21 | D83: 42856 | E83: 1 | F83: 1 | G83: 8596565 | H83: CUADRE FABRICA | I83: 1 | J83: 11000 | K83: 0 | L83: 1 | N83: 0
A84: =+A83+1 -> 83 | B84: 529530 | C84: 21 | D84: 42856 | E84: 1 | F84: 4840 | G84: 860512330 | H84: CUADRE FABRICA | I84: 1 | J84: 21000 | K84: 0 | L84: 1 | N84: 0
A85: =+A84+1 -> 84 | B85: 529525 | C85: 21 | D85: 42856 | E85: 1 | F85: 5809 | G85: 890935426 | H85: CUADRE FABRICA | I85: 1 | J85: 34005 | K85: 0 | L85: 1 | N85: 0
A86: =+A85+1 -> 85 | B86: 11050501 | C86: 21 | D86: 42887 | E86: 1 | F86: 1 | H86: CUADRE FABRICA | I86: 2 | J86: 13614664 | K86: 0 | N86: 0
A87: =+A86+1 -> 86 | B87: 11100507 | C87: 21 | D87: 42887 | E87: 1 | F87: 2568 | H87: CUADRE FABRICA | I87: 1 | J87: 14605 | K87: 0 | N87: 0
A88: =+A87+1 -> 87 | B88: 11100507 | C88: 21 | D88: 42887 | E88: 1 | F88: 2571 | H88: CUADRE FABRICA | I88: 1 | J88: 588000 | K88: 0 | N88: 0
A89: =+A88+1 -> 88 | B89: 11100507 | C89: 21 | D89: 42887 | E89: 1 | F89: 9502 | H89: CUADRE FABRICA | I89: 1 | J89: 229732 | K89: 0 | N89: 0
A90: =+A89+1 -> 89 | B90: 11201010 | C90: 21 | D90: 42887 | E90: 1 | F90: 7808 | H90: CUADRE FABRICA | I90: 1 | J90: 226000 | K90: 0 | N90: 0
A91: =+A90+1 -> 90 | B91: 11050500 | C91: 21 | D91: 42887 | E91: 1 | F91: 1 | H91: CUADRE FABRICA CON/CO/DIC | I91: 1 | J91: 10067302 | K91: 0 | N91: 0
A92: =+A91+1 -> 91 | B92: 11201010 | C92: 21 | D92: 42887 | E92: 1 | F92: 1 | H92: CUADRE FABRICA CON/CO/DIC | I92: 1 | J92: 801156 | K92: 0 | N92: 0
A93: =+A92+1 -> 92 | B93: 11201010 | C93: 21 | D93: 42887 | E93: 1 | F93: 1 | H93: CUADRE FABRICA | I93: 1 | J93: 1200499 | K93: 0 | N93: 0
A94: =+A93+1 -> 93 | B94: 11050500 | C94: 21 | D94: 42887 | E94: 1 | F94: 7576 | H94: CUADRE FABRICA | I94: 1 | J94: 59974 | K94: 0 | N94: 0
A95: =+A94+1 -> 94 | B95: 11050500 | C95: 21 | D95: 42887 | E95: 1 | F95: 7578 | H95: CUADRE FABRICA | I95: 1 | J95: 299700 | K95: 0 | N95: 0
A96: =+A95+1 -> 95 | B96: 11050500 | C96: 21 | D96: 42887 | E96: 1 | F96: 1 | H96: CUADRE FABRICA | I96: 1 | J96: 54875 | K96: 0 | N96: 0
A97: =+A96+1 -> 96 | B97: 524540 | C97: 21 | D97: 42887 | E97: 1 | F97: 1 | G97: 32210056 | H97: CUADRE FABRICA | I97: 1 | J97: 12000 | K97: 0 | L97: 1 | N97: 0
A98: =+A97+1 -> 97 | B98: 52359520 | C98: 21 | D98: 42887 | E98: 1 | F98: 3066 | G98: 1036598278 | H98: CUADRE FABRICA | I98: 1 | J98: 15000 | K98: 0 | L98: 1 | N98: 0
A99: =+A98+1 -> 98 | B99: 524540 | C99: 21 | D99: 42887 | E99: 1 | F99: 1740 | G99: 890931835 | H99: CUADRE FABRICA | I99: 1 | J99: 14132 | K99: 0 | L99: 1 | N99: 0
A100: =+A99+1 -> 99 | B100: 529530 | C100: 21 | D100: 42887 | E100: 1 | F100: 1312 | G100: 98639602 | H100: CUADRE FABRICA | I100: 1 | J100: 24001 | K100: 0 | L100: 1 | N100: 0
...

Sheet Hoja9
A1: 7841 | B1: 1 | C1: f | D1: 14301000 | E1: 1 | F1: 42760 | G1: 51779 | H1: 51779 | J1: Valor Inv. Docto 000051779 | K1: 2 | L1: 528193 | M1: 0 | P1: 0 | Y1: 1 | Z1: 1 | AA1: 1 | AB1: 1 | AC1: 43511.928 | AD1: 43511.928
A2: 7842 | B2: 1 | C2: f | D2: 24080120 | E2: 1 | F2: 42760 | G2: 51779 | H2: 51779 | I2: 39636059 | J2: Valor I.V.A Docto 000051779 | K2: 2 | L2: 19339 | M2: 193395 | P2: 0 | Y2: 1 | Z2: 1 | AA2: 1 | AB2: 1 | AC2: 43511.928 | AD2: 43511.928
A3: 7843 | B3: 1 | C3: f | D3: 41200907 | E3: 1 | F3: 42760 | G3: 51779 | H3: 51779 | I3: 39636059 | J3: VENTAS CREDITO FABRICA | K3: 2 | L3: 193395 | M3: 0 | N3: 1 | P3: 0 | Y3: 1 | Z3: 1 | AA3: 1 | AB3: 1 | AC3: 43511.928 | AD3: 43511.928
A4: 7844 | B4: 1 | C4: f | D4: 61200900 | E4: 1 | F4: 42760 | G4: 51779 | H4: 51779 | J4: Valor Costo Docto 000051779 | K4: 1 | L4: 528193 | M4: 0 | P4: 0 | Y4: 1 | Z4: 1 | AA4: 1 | AB4: 1 | AC4: 43511.928 | AD4: 43511.928
A5: 7845 | B5: 1 | C5: f | D5: 13050510 | E5: 1 | F5: 42760 | G5: 51780 | H5: 51780 | I5: 30238105 | J5: VLR TOTAL DOC 000051780 | K5: 1 | L5: 60999 | M5: 0 | P5: 0 | Y5: 1 | Z5: 1 | AA5: 1 | AB5: 1 | AC5: 43511.928 | AD5: 43511.928
A6: 7846 | B6: 1 | C6: f | D6: 14301000 | E6: 1 | F6: 42760 | G6: 51780 | H6: 51780 | J6: Valor Inv. Docto 000051780 | K6: 2 | L6: 64873 | M6: 0 | P6: 0 | Y6: 1 | Z6: 1 | AA6: 1 | AB6: 1 | AC6: 43511.928 | AD6: 43511.928
A7: 7847 | B7: 1 | C7: f | D7: 24080120 | E7: 1 | F7: 42760 | G7: 51780 | H7: 51780 | I7: 30238105 | J7: Valor I.V.A Docto 000051780 | K7: 2 | L7: 5545 | M7: 55454 | P7: 0 | Y7: 1 | Z7: 1 | AA7: 1 | AB7: 1 | AC7: 43511.928 | AD7: 43511.928
A8: 7848 | B8: 1 | C8: f | D8: 41200907 | E8: 1 | F8: 42760 | G8: 51780 | H8: 51780 | I8: 30238105 | J8: VENTAS CREDITO FABRICA | K8: 2 | L8: 55454 | M8: 0 | N8: 1 | P8: 0 | Y8: 1 | Z8: 1 | AA8: 1 | AB8: 1 | AC8: 43511.928 | AD8: 43511.928
A9: 7849 | B9: 1 | C9: f | D9: 61200900 | E9: 1 | F9: 42760 | G9: 51780 | H9: 51780 | J9: Valor Costo Docto 000051780 | K9: 1 | L9: 64873 | M9: 0 | P9: 0 | Y9: 1 | Z9: 1 | AA9: 1 | AB9: 1 | AC9: 43511.928 | AD9: 43511.928
A10: 7850 | B10: 1 | C10: f | D10: 13050510 | E10: 1 | F10: 42760 | G10: 51781 | H10: 51781 | I10: 7422201 | J10: VLR TOTAL DOC 000051781 | K10: 1 | L10: 295522 | M10: 0 | P10: 15 | Y10: 1 | Z10: 1 | AA10: 1 | AB10: 1 | AC10: 43511.928 | AD10: 43511.928
A11: 7851 | B11: 1 | C11: f | D11: 14301000 | E11: 1 | F11: 42760 | G11: 51781 | H11: 51781 | J11: Valor Inv. Docto 000051781 | K11: 2 | L11: 648712 | M11: 0 | P11: 15 | Y11: 1 | Z11: 1 | AA11: 1 | AB11: 1 | AC11: 43511.928 | AD11: 43511.928
A12: 7852 | B12: 1 | C12: f | D12: 24080120 | E12: 1 | F12: 42760 | G12: 51781 | H12: 51781 | I12: 7422201 | J12: Valor I.V.A Docto 000051781 | K12: 2 | L12: 26866 | M12: 268656 | P12: 15 | Y12: 1 | Z12: 1 | AA12: 1 | AB12: 1 | AC12: 43511.928 | AD12: 43511.928
A13: 7853 | B13: 1 | C13: f | D13: 41200907 | E13: 1 | F13: 42760 | G13: 51781 | H13: 51781 | I13: 7422201 | J13: VENTAS CREDITO FABRICA | K13: 2 | L13: 268656 | M13: 0 | N13: 1 | P13: 15 | Y13: 1 | Z13: 1 | AA13: 1 | AB13: 1 | AC13: 43511.928 | AD13: 43511.928
A14: 7854 | B14: 1 | C14: f | D14: 61200900 | E14: 1 | F14: 42760 | G14: 51781 | H14: 51781 | J14: Valor Costo Docto 000051781 | K14: 1 | L14: 648712 | M14: 0 | P14: 15 | Y14: 1 | Z14: 1 | AA14: 1 | AB14: 1 | AC14: 43511.928 | AD14: 43511.928
A15: 7855 | B15: 1 | C15: f | D15: 13050510 | E15: 1 | F15: 42760 | G15: 51782 | H15: 51782 | I15: 10273897 | J15: VLR TOTAL DOC 000051782 | K15: 1 | L15: 544161 | M15: 0 | P15: 8 | Y15: 1 | Z15: 1 | AA15: 1 | AB15: 1 | AC15: 43511.928 | AD15: 43511.928
A16: 7856 | B16: 1 | C16: f | D16: 14301000 | E16: 1 | F16: 42760 | G16: 51782 | H16: 51782 | J16: Valor Inv. Docto 000051782 | K16: 2 | L16: 435328 | M16: 0 | P16: 0 | Y16: 1 | Z16: 1 | AA16: 1 | AB16: 1 | AC16: 43511.928 | AD16: 43511.928
A17: 7857 | B17: 1 | C17: f | D17: 24080120 | E17: 1 | F17: 42760 | G17: 51782 | H17: 51782 | I17: 10273897 | J17: Valor I.V.A Docto 000051782 | K17: 2 | L17: 49469 | M17: 494692 | P17: 8 | Y17: 1 | Z17: 1 | AA17: 1 | AB17: 1 | AC17: 43511.928 | AD17: 43511.928
A18: 7858 | B18: 1 | C18: f | D18: 41200907 | E18: 1 | F18: 42760 | G18: 51782 | H18: 51782 | I18: 10273897 | J18: VENTAS CREDITO FABRICA | K18: 2 | L18: 494692 | M18: 0 | N18: 1 | P18: 8 | Y18: 1 | Z18: 1 | AA18: 1 | AB18: 1 | AC18: 43511.928 | AD18: 43511.928
A19: 7859 | B19: 1 | C19: f | D19: 61200900 | E19: 1 | F19: 42760 | G19: 51782 | H19: 51782 | J19: Valor Costo Docto 000051782 | K19: 1 | L19: 435328 | M19: 0 | P19: 0 | Y19: 1 | Z19: 1 | AA19: 1 | AB19: 1 | AC19: 43511.928 | AD19: 43511.928
A20: 7860 | B20: 1 | C20: f | D20: 13050510 | E20: 1 | F20: 42760 | G20: 51783 | H20: 51783 | I20: 1 | J20: VLR TOTAL DOC 000051783 | K20: 1 | L20: 12350 | M20: 0 | P20: 0 | Y20: 1 | Z20: 1 | AA20: 1 | AB20: 1 | AC20: 43511.928 | AD20: 43511.928
A21: 7861 | B21: 1 | C21: f | D21: 14301000 | E21: 1 | F21: 42760 | G21: 51783 | H21: 51783 | J21: Valor Inv. Docto 000051783 | K21: 2 | L21: 11321 | M21: 0 | P21: 0 | Y21: 1 | Z21: 1 | AA21: 1 | AB21: 1 | AC21: 43511.928 | AD21: 43511.928
A22: 7862 | B22: 1 | C22: f | D22: 24080120 | E22: 1 | F22: 42760 | G22: 51783 | H22: 51783 | I22: 1 | J22: Valor I.V.A Docto 000051783 | K22: 2 | L22: 1123 | M22: 11227 | P22: 0 | Y22: 1 | Z22: 1 | AA22: 1 | AB22: 1 | AC22: 43511.928 | AD22: 43511.928
A23: 7863 | B23: 1 | C23: f | D23: 41200907 | E23: 1 | F23: 42760 | G23: 51783 | H23: 51783 | I23: 1 | J23: VENTAS CREDITO FABRICA | K23: 2 | L23: 11227 | M23: 0 | N23: 1 | P23: 0 | Y23: 1 | Z23: 1 | AA23: 1 | AB23: 1 | AC23: 43511.928 | AD23: 43511.928
A24: 7864 | B24: 1 | C24: f | D24: 61200900 | E24: 1 | F24: 42760 | G24: 51783 | H24: 51783 | J24: Valor Costo Docto 000051783 | K24: 1 | L24: 11321 | M24: 0 | P24: 0 | Y24: 1 | Z24: 1 | AA24: 1 | AB24: 1 | AC24: 43511.928 | AD24: 43511.928
A25: 7865 | B25: 1 | C25: f | D25: 13050510 | E25: 1 | F25: 42760 | G25: 51784 | H25: 51784 | I25: 66963257 | J25: VLR TOTAL DOC 000051784 | K25: 1 | L25: 80791 | M25: 0 | P25: 0 | Y25: 1 | Z25: 1 | AA25: 1 | AB25: 1 | AC25: 43511.928 | AD25: 43511.928
A26: 7866 | B26: 1 | C26: f | D26: 14301000 | E26: 1 | F26: 42760 | G26: 51784 | H26: 51784 | J26: Valor Inv. Docto 000051784 | K26: 2 | L26: 135203 | M26: 0 | P26: 0 | Y26: 1 | Z26: 1 | AA26: 1 | AB26: 1 | AC26: 43511.928 | AD26: 43511.928
A27: 7867 | B27: 1 | C27: f | D27: 24080120 | E27: 1 | F27: 42760 | G27: 51784 | H27: 51784 | I27: 66963257 | J27: Valor I.V.A Docto 000051784 | K27: 2 | L27: 7345 | M27: 73446 | P27: 0 | Y27: 1 | Z27: 1 | AA27: 1 | AB27: 1 | AC27: 43511.928 | AD27: 43511.928
A28: 7868 | B28: 1 | C28: f | D28: 41200907 | E28: 1 | F28: 42760 | G28: 51784 | H28: 51784 | I28: 66963257 | J28: VENTAS CREDITO FABRICA | K28: 2 | L28: 73446 | M28: 0 | N28: 1 | P28: 0 | Y28: 1 | Z28: 1 | AA28: 1 | AB28: 1 | AC28: 43511.928 | AD28: 43511.928
A29: 7869 | B29: 1 | C29: f | D29: 61200900 | E29: 1 | F29: 42760 | G29: 51784 | H29: 51784 | J29: Valor Costo Docto 000051784 | K29: 1 | L29: 135203 | M29: 0 | P29: 0 | Y29: 1 | Z29: 1 | AA29: 1 | AB29: 1 | AC29: 43511.928 | AD29: 43511.928
A30: 7870 | B30: 1 | C30: f | D30: 13050510 | E30: 1 | F30: 42760 | G30: 51785 | H30: 51785 | I30: 71718340 | J30: VLR TOTAL DOC 000051785 | K30: 1 | L30: 71975 | M30: 0 | P30: 8 | Y30: 1 | Z30: 1 | AA30: 1 | AB30: 1 | AC30: 43511.928 | AD30: 43511.928
A31: 7871 | B31: 1 | C31: f | D31: 14301000 | E31: 1 | F31: 42760 | G31: 51785 | H31: 51785 | J31: Valor Inv. Docto 000051785 | K31: 2 | L31: 119573 | M31: 0 | P31: 8 | Y31: 1 | Z31: 1 | AA31: 1 | AB31: 1 | AC31: 43511.928 | AD31: 43511.928
A32: 7872 | B32: 1 | C32: f | D32: 24080120 | E32: 1 | F32: 42760 | G32: 51785 | H32: 51785 | I32: 71718340 | J32: Valor I.V.A Docto 000051785 | K32: 2 | L32: 6543 | M32: 65432 | P32: 8 | Y32: 1 | Z32: 1 | AA32: 1 | AB32: 1 | AC32: 43511.928 | AD32: 43511.928
A33: 7873 | B33: 1 | C33: f | D33: 41200907 | E33: 1 | F33: 42760 | G33: 51785 | H33: 51785 | I33: 71718340 | J33: VENTAS CREDITO FABRICA | K33: 2 | L33: 65432 | M33: 0 | N33: 1 | P33: 8 | Y33: 1 | Z33: 1 | AA33: 1 | AB33: 1 | AC33: 43511.928 | AD33: 43511.928
A34: 7874 | B34: 1 | C34: f | D34: 61200900 | E34: 1 | F34: 42760 | G34: 51785 | H34: 51785 | J34: Valor Costo Docto 000051785 | K34: 1 | L34: 119573 | M34: 0 | P34: 8 | Y34: 1 | Z34: 1 | AA34: 1 | AB34: 1 | AC34: 43511.928 | AD34: 43511.928
A35: 7875 | B35: 1 | C35: f | D35: 13050510 | E35: 1 | F35: 42760 | G35: 51786 | H35: 51786 | I35: 42763194 | J35: VLR TOTAL DOC 000051786 | K35: 1 | L35: 26270 | M35: 0 | P35: 0 | Y35: 1 | Z35: 1 | AA35: 1 | AB35: 1 | AC35: 43511.928 | AD35: 43511.928
A36: 7876 | B36: 1 | C36: f | D36: 14301000 | E36: 1 | F36: 42760 | G36: 51786 | H36: 51786 | J36: Valor Inv. Docto 000051786 | K36: 2 | L36: 75009 | M36: 0 | P36: 0 | Y36: 1 | Z36: 1 | AA36: 1 | AB36: 1 | AC36: 43511.928 | AD36: 43511.928
A37: 7877 | B37: 1 | C37: f | D37: 24080120 | E37: 1 | F37: 42760 | G37: 51786 | H37: 51786 | I37: 42763194 | J37: Valor I.V.A Docto 000051786 | K37: 2 | L37: 2388 | M37: 23882 | P37: 0 | Y37: 1 | Z37: 1 | AA37: 1 | AB37: 1 | AC37: 43511.928 | AD37: 43511.928
A38: 7878 | B38: 1 | C38: f | D38: 41200907 | E38: 1 | F38: 42760 | G38: 51786 | H38: 51786 | I38: 42763194 | J38: VENTAS CREDITO FABRICA | K38: 2 | L38: 23882 | M38: 0 | N38: 1 | P38: 0 | Y38: 1 | Z38: 1 | AA38: 1 | AB38: 1 | AC38: 43511.928 | AD38: 43511.928
A39: 7879 | B39: 1 | C39: f | D39: 61200900 | E39: 1 | F39: 42760 | G39: 51786 | H39: 51786 | J39: Valor Costo Docto 000051786 | K39: 1 | L39: 75009 | M39: 0 | P39: 0 | Y39: 1 | Z39: 1 | AA39: 1 | AB39: 1 | AC39: 43511.928 | AD39: 43511.928
A40: 7880 | B40: 1 | C40: f | D40: 13050510 | E40: 1 | F40: 42760 | G40: 51787 | H40: 51787 | I40: 1 | J40: VLR TOTAL DOC 000051787 | K40: 1 | L40: 4421 | M40: 0 | P40: 0 | Y40: 1 | Z40: 1 | AA40: 1 | AB40: 1 | AC40: 43511.928 | AD40: 43511.928
A41: 7881 | B41: 1 | C41: f | D41: 14301000 | E41: 1 | F41: 42760 | G41: 51787 | H41: 51787 | J41: Valor Inv. Docto 000051787 | K41: 2 | L41: 6488 | M41: 0 | P41: 0 | Y41: 1 | Z41: 1 | AA41: 1 | AB41: 1 | AC41: 43511.928 | AD41: 43511.928
A42: 7882 | B42: 1 | C42: f | D42: 24080120 | E42: 1 | F42: 42760 | G42: 51787 | H42: 51787 | I42: 1 | J42: Valor I.V.A Docto 000051787 | K42: 2 | L42: 402 | M42: 4019 | P42: 0 | Y42: 1 | Z42: 1 | AA42: 1 | AB42: 1 | AC42: 43511.928 | AD42: 43511.928
A43: 7883 | B43: 1 | C43: f | D43: 41200907 | E43: 1 | F43: 42760 | G43: 51787 | H43: 51787 | I43: 1 | J43: VENTAS CREDITO FABRICA | K43: 2 | L43: 4019 | M43: 0 | N43: 1 | P43: 0 | Y43: 1 | Z43: 1 | AA43: 1 | AB43: 1 | AC43: 43511.928 | AD43: 43511.928
A44: 7884 | B44: 1 | C44: f | D44: 61200900 | E44: 1 | F44: 42760 | G44: 51787 | H44: 51787 | J44: Valor Costo Docto 000051787 | K44: 1 | L44: 6488 | M44: 0 | P44: 0 | Y44: 1 | Z44: 1 | AA44: 1 | AB44: 1 | AC44: 43511.928 | AD44: 43511.928
A45: 7885 | B45: 1 | C45: f | D45: 13050510 | E45: 1 | F45: 42760 | G45: 51788 | H45: 51788 | I45: 890900608 | J45: VLR TOTAL DOC 000051788 | K45: 1 | L45: 321483 | M45: 0 | P45: 30 | Y45: 1 | Z45: 1 | AA45: 1 | AB45: 1 | AC45: 43511.928 | AD45: 43511.928
A46: 7886 | B46: 1 | C46: f | D46: 14301000 | E46: 1 | F46: 42760 | G46: 51788 | H46: 51788 | J46: Valor Inv. Docto 000051788 | K46: 2 | L46: 499515 | M46: 0 | P46: 30 | Y46: 1 | Z46: 1 | AA46: 1 | AB46: 1 | AC46: 43511.928 | AD46: 43511.928
A47: 7887 | B47: 1 | C47: f | D47: 24080120 | E47: 1 | F47: 42760 | G47: 51788 | H47: 51788 | I47: 890900608 | J47: Valor I.V.A Docto 000051788 | K47: 2 | L47: 29226 | M47: 292257 | P47: 30 | Y47: 1 | Z47: 1 | AA47: 1 | AB47: 1 | AC47: 43511.928 | AD47: 43511.928
A48: 7888 | B48: 1 | C48: f | D48: 41200907 | E48: 1 | F48: 42760 | G48: 51788 | H48: 51788 | I48: 890900608 | J48: VENTAS CREDITO FABRICA | K48: 2 | L48: 292257 | M48: 0 | N48: 1 | P48: 30 | Y48: 1 | Z48: 1 | AA48: 1 | AB48: 1 | AC48: 43511.928 | AD48: 43511.928
A49: 7889 | B49: 1 | C49: f | D49: 61200900 | E49: 1 | F49: 42760 | G49: 51788 | H49: 51788 | J49: Valor Costo Docto 000051788 | K49: 1 | L49: 499515 | M49: 0 | P49: 30 | Y49: 1 | Z49: 1 | AA49: 1 | AB49: 1 | AC49: 43511.928 | AD49: 43511.928
A50: 7890 | B50: 1 | C50: f | D50: 13050510 | E50: 1 | F50: 42760 | G50: 51790 | H50: 51790 | I50: 599 | J50: VLR TOTAL DOC 000051790 | K50: 1 | L50: 215849 | M50: 0 | P50: 0 | Y50: 1 | Z50: 1 | AA50: 1 | AB50: 1 | AC50: 43511.928 | AD50: 43511.928
A51: 7891 | B51: 1 | C51: f | D51: 14301000 | E51: 1 | F51: 42760 | G51: 51790 | H51: 51790 | J51: Valor Inv. Docto 000051790 | K51: 2 | L51: 172679 | M51: 0 | P51: 0 | Y51: 1 | Z51: 1 | AA51: 1 | AB51: 1 | AC51: 43511.928 | AD51: 43511.928
A52: 7892 | B52: 1 | C52: f | D52: 24080120 | E52: 1 | F52: 42760 | G52: 51790 | H52: 51790 | I52: 599 | J52: Valor I.V.A Docto 000051790 | K52: 2 | L52: 19622 | M52: 196227 | P52: 0 | Y52: 1 | Z52: 1 | AA52: 1 | AB52: 1 | AC52: 43511.928 | AD52: 43511.928
A53: 7893 | B53: 1 | C53: f | D53: 41200907 | E53: 1 | F53: 42760 | G53: 51790 | H53: 51790 | I53: 599 | J53: VENTAS CREDITO FABRICA | K53: 2 | L53: 196227 | M53: 0 | N53: 1 | P53: 0 | Y53: 1 | Z53: 1 | AA53: 1 | AB53: 1 | AC53: 43511.928 | AD53: 43511.928
A54: 7894 | B54: 1 | C54: f | D54: 61200900 | E54: 1 | F54: 42760 | G54: 51790 | H54: 51790 | J54: Valor Costo Docto 000051790 | K54: 1 | L54: 172679 | M54: 0 | P54: 0 | Y54: 1 | Z54: 1 | AA54: 1 | AB54: 1 | AC54: 43511.928 | AD54: 43511.928
A55: 7895 | B55: 1 | C55: f | D55: 13050510 | E55: 1 | F55: 42760 | G55: 51791 | H55: 51791 | I55: 599 | J55: VLR TOTAL DOC 000051791 | K55: 1 | L55: 115500 | M55: 0 | P55: 0 | Y55: 1 | Z55: 1 | AA55: 1 | AB55: 1 | AC55: 43511.928 | AD55: 43511.928
A56: 7896 | B56: 1 | C56: f | D56: 14301000 | E56: 1 | F56: 42760 | G56: 51791 | H56: 51791 | J56: Valor Inv. Docto 000051791 | K56: 2 | L56: 700572 | M56: 0 | P56: 0 | Y56: 1 | Z56: 1 | AA56: 1 | AB56: 1 | AC56: 43511.928 | AD56: 43511.928
A57: 7897 | B57: 1 | C57: f | D57: 24080120 | E57: 1 | F57: 42760 | G57: 51791 | H57: 51791 | I57: 599 | J57: Valor I.V.A Docto 000051791 | K57: 2 | L57: 10500 | M57: 105000 | P57: 0 | Y57: 1 | Z57: 1 | AA57: 1 | AB57: 1 | AC57: 43511.928 | AD57: 43511.928
A58: 7898 | B58: 1 | C58: f | D58: 41200907 | E58: 1 | F58: 42760 | G58: 51791 | H58: 51791 | I58: 599 | J58: VENTAS CREDITO FABRICA | K58: 2 | L58: 105000 | M58: 0 | N58: 1 | P58: 0 | Y58: 1 | Z58: 1 | AA58: 1 | AB58: 1 | AC58: 43511.928 | AD58: 43511.928
A59: 7899 | B59: 1 | C59: f | D59: 61200900 | E59: 1 | F59: 42760 | G59: 51791 | H59: 51791 | J59: Valor Costo Docto 000051791 | K59: 1 | L59: 700572 | M59: 0 | P59: 0 | Y59: 1 | Z59: 1 | AA59: 1 | AB59: 1 | AC59: 43511.928 | AD59: 43511.928
A60: 7900 | B60: 1 | C60: f | D60: 13050510 | E60: 18 | F60: 42760 | G60: 11989 | H60: 51756 | I60: 71723345 | J60: VLR TOTAL DOC 000011989 | K60: 2 | L60: 9570 | M60: 0 | P60: 0 | Y60: 1 | Z60: 1 | AA60: 1 | AB60: 1 | AC60: 43511.928 | AD60: 43511.928
A61: 7901 | B61: 1 | C61: f | D61: 24080207 | E61: 18 | F61: 42760 | G61: 11989 | H61: 51756 | I61: 71723345 | J61: Valor I.V.A Docto 000011989 | K61: 1 | L61: 870 | M61: 8700 | N61: 1 | P61: 0 | Y61: 1 | Z61: 1 | AA61: 1 | AB61: 1 | AC61: 43511.928 | AD61: 43511.928
A62: 7902 | B62: 1 | C62: f | D62: 41750107 | E62: 18 | F62: 42760 | G62: 11989 | H62: 51756 | I62: 71723345 | J62: NC DEV. POR DETERIORO 10% | K62: 1 | L62: 8700 | M62: 0 | N62: 1 | P62: 0 | Y62: 1 | Z62: 1 | AA62: 1 | AB62: 1 | AC62: 43511.928 | AD62: 43511.928
A63: 7903 | B63: 1 | C63: f | D63: 53104000 | E63: 18 | F63: 42760 | G63: 11989 | H63: 51756 | I63: 71723345 | J63: Valor Inv. Docto 000011989 | K63: 1 | L63: 9570 | M63: 0 | P63: 0 | Y63: 1 | Z63: 1 | AA63: 1 | AB63: 1 | AC63: 43511.928 | AD63: 43511.928
A64: 7904 | B64: 1 | C64: f | D64: 61200900 | E64: 18 | F64: 42760 | G64: 11989 | H64: 51756 | J64: Valor Costo Docto 000011989 | K64: 2 | L64: 9570 | M64: 0 | P64: 0 | Y64: 1 | Z64: 1 | AA64: 1 | AB64: 1 | AC64: 43511.928 | AD64: 43511.928
A65: 7905 | B65: 1 | C65: f | D65: 13050510 | E65: 18 | F65: 42760 | G65: 11990 | H65: 51725 | I65: 43046030 | J65: VLR TOTAL DOC 000011990 | K65: 2 | L65: 8842 | M65: 0 | P65: 0 | Y65: 1 | Z65: 1 | AA65: 1 | AB65: 1 | AC65: 43511.928 | AD65: 43511.928
A66: 7906 | B66: 1 | C66: f | D66: 24080207 | E66: 18 | F66: 42760 | G66: 11990 | H66: 51725 | I66: 43046030 | J66: Valor I.V.A Docto 000011990 | K66: 1 | L66: 804 | M66: 8038 | N66: 1 | P66: 0 | Y66: 1 | Z66: 1 | AA66: 1 | AB66: 1 | AC66: 43511.928 | AD66: 43511.928
A67: 7907 | B67: 1 | C67: f | D67: 41750107 | E67: 18 | F67: 42760 | G67: 11990 | H67: 51725 | I67: 43046030 | J67: NC DEV. POR DETERIORO 10% | K67: 1 | L67: 8038 | M67: 0 | N67: 1 | P67: 0 | Y67: 1 | Z67: 1 | AA67: 1 | AB67: 1 | AC67: 43511.928 | AD67: 43511.928
A68: 7908 | B68: 1 | C68: f | D68: 53104000 | E68: 18 | F68: 42760 | G68: 11990 | H68: 51725 | I68: 43046030 | J68: Valor Inv. Docto 000011990 | K68: 1 | L68: 202 | M68: 0 | P68: 0 | Y68: 1 | Z68: 1 | AA68: 1 | AB68: 1 | AC68: 43511.928 | AD68: 43511.928
A69: 7909 | B69: 1 | C69: f | D69: 61200900 | E69: 18 | F69: 42760 | G69: 11990 | H69: 51725 | J69: Valor Costo Docto 000011990 | K69: 2 | L69: 202 | M69: 0 | P69: 0 | Y69: 1 | Z69: 1 | AA69: 1 | AB69: 1 | AC69: 43511.928 | AD69: 43511.928
A70: 7910 | B70: 1 | C70: f | D70: 13050510 | E70: 18 | F70: 42760 | G70: 11991 | H70: 51766 | I70: 8353246 | J70: VLR TOTAL DOC 000011991 | K70: 2 | L70: 12760 | M70: 0 | P70: 0 | Y70: 1 | Z70: 1 | AA70: 1 | AB70: 1 | AC70: 43511.928 | AD70: 43511.928
A71: 7911 | B71: 1 | C71: f | D71: 24080207 | E71: 18 | F71: 42760 | G71: 11991 | H71: 51766 | I71: 8353246 | J71: Valor I.V.A Docto 000011991 | K71: 1 | L71: 1160 | M71: 11600 | N71: 1 | P71: 0 | Y71: 1 | Z71: 1 | AA71: 1 | AB71: 1 | AC71: 43511.928 | AD71: 43511.928
A72: 7912 | B72: 1 | C72: f | D72: 41750107 | E72: 18 | F72: 42760 | G72: 11991 | H72: 51766 | I72: 8353246 | J72: NC ANULACION VENTAS 10% | K72: 1 | L72: 11600 | M72: 0 | N72: 1 | P72: 0 | Y72: 1 | Z72: 1 | AA72: 1 | AB72: 1 | AC72: 43511.928 | AD72: 43511.928
A73: 7913 | B73: 1 | C73: f | D73: 53104000 | E73: 18 | F73: 42760 | G73: 11991 | H73: 51766 | I73: 8353246 | J73: Valor Inv. Docto 000011991 | K73: 1 | L73: 10966 | M73: 0 | P73: 0 | Y73: 1 | Z73: 1 | AA73: 1 | AB73: 1 | AC73: 43511.928 | AD73: 43511.928
A74: 7914 | B74: 1 | C74: f | D74: 61200900 | E74: 18 | F74: 42760 | G74: 11991 | H74: 51766 | J74: Valor Costo Docto 000011991 | K74: 2 | L74: 10966 | M74: 0 | P74: 0 | Y74: 1 | Z74: 1 | AA74: 1 | AB74: 1 | AC74: 43511.928 | AD74: 43511.928
A75: 7915 | B75: 1 | C75: f | D75: 13050510 | E75: 18 | F75: 42760 | G75: 11992 | H75: 51653 | I75: 32321806 | J75: VLR TOTAL DOC 000011992 | K75: 2 | L75: 153864 | M75: 0 | P75: 15 | Y75: 1 | Z75: 1 | AA75: 1 | AB75: 1 | AC75: 43511.928 | AD75: 43511.928
A76: 7916 | B76: 1 | C76: f | D76: 24080207 | E76: 18 | F76: 42760 | G76: 11992 | H76: 51653 | I76: 32321806 | J76: Valor I.V.A Docto 000011992 | K76: 1 | L76: 13988 | M76: 139877 | N76: 1 | P76: 15 | Y76: 1 | Z76: 1 | AA76: 1 | AB76: 1 | AC76: 43511.928 | AD76: 43511.928
A77: 7917 | B77: 1 | C77: f | D77: 41750107 | E77: 18 | F77: 42760 | G77: 11992 | H77: 51653 | I77: 32321806 | J77: NC ANULACION VENTAS 10% | K77: 1 | L77: 139876 | M77: 0 | N77: 1 | P77: 15 | Y77: 1 | Z77: 1 | AA77: 1 | AB77: 1 | AC77: 43511.928 | AD77: 43511.928
A78: 7918 | B78: 1 | C78: f | D78: 53104001 | E78: 18 | F78: 42760 | G78: 11992 | H78: 51653 | I78: 32321806 | J78: Valor Inv. Docto 000011992 | K78: 1 | L78: 110839 | M78: 0 | P78: 0 | Y78: 1 | Z78: 1 | AA78: 1 | AB78: 1 | AC78: 43511.928 | AD78: 43511.928
A79: 7919 | B79: 1 | C79: f | D79: 61200900 | E79: 18 | F79: 42760 | G79: 11992 | H79: 51653 | J79: Valor Costo Docto 000011992 | K79: 2 | L79: 110839 | M79: 0 | P79: 15 | Y79: 1 | Z79: 1 | AA79: 1 | AB79: 1 | AC79: 43511.928 | AD79: 43511.928
A80: 7920 | B80: 1 | C80: f | D80: 13050510 | E80: 2 | F80: 42760 | G80: 28319 | H80: 51777 | I80: 599 | J80: RC CLIENTES CREDITO | K80: 2 | L80: 16500 | M80: 0 | O80: 90 | P80: 0 | Y80: 1 | Z80: 1 | AA80: 1 | AB80: 1 | AC80: 43511.928 | AD80: 43511.928
A81: 7921 | B81: 1 | C81: f | D81: 13050510 | E81: 2 | F81: 42760 | G81: 28319 | H81: 51776 | I81: 599 | J81: RC CLIENTES CREDITO | K81: 2 | L81: 16500 | M81: 0 | O81: 90 | P81: 0 | Y81: 1 | Z81: 1 | AA81: 1 | AB81: 1 | AC81: 43511.928 | AD81: 43511.928
A82: 7922 | B82: 1 | C82: f | D82: 13050510 | E82: 2 | F82: 42760 | G82: 28319 | H82: 51791 | I82: 599 | J82: RC CLIENTES CREDITO | K82: 2 | L82: 115500 | M82: 0 | O82: 90 | P82: 0 | Y82: 1 | Z82: 1 | AA82: 1 | AB82: 1 | AC82: 43511.928 | AD82: 43511.928
A83: 7923 | B83: 1 | C83: f | D83: 13050510 | E83: 2 | F83: 42760 | G83: 28319 | H83: 51790 | I83: 599 | J83: RC CLIENTES CREDITO | K83: 2 | L83: 215849 | M83: 0 | O83: 90 | P83: 0 | Y83: 1 | Z83: 1 | AA83: 1 | AB83: 1 | AC83: 43511.928 | AD83: 43511.928
A84: 7924 | B84: 1 | C84: f | D84: 11050501 | E84: 2 | F84: 42760 | G84: 28319 | H84: 0 | J84: VLR TOTAL DOC 000028319 | K84: 1 | L84: 364349 | M84: 0 | O84: 90 | P84: 0 | Y84: 1 | Z84: 1 | AA84: 1 | AB84: 1 | AC84: 43511.928 | AD84: 43511.928
A85: 7925 | B85: 1 | C85: f | D85: 13050510 | E85: 2 | F85: 42760 | G85: 28320 | H85: 51783 | I85: 1 | J85: RC CLIENTES CREDITO | K85: 2 | L85: 12350 | M85: 0 | O85: 90 | P85: 1 | Y85: 1 | Z85: 1 | AA85: 1 | AB85: 1 | AC85: 43511.928 | AD85: 43511.928
A86: 7926 | B86: 1 | C86: f | D86: 13050510 | E86: 2 | F86: 42760 | G86: 28320 | H86: 51763 | I86: 1 | J86: RC CLIENTES CREDITO | K86: 2 | L86: 5250 | M86: 0 | O86: 90 | P86: 1 | Y86: 1 | Z86: 1 | AA86: 1 | AB86: 1 | AC86: 43511.928 | AD86: 43511.928
A87: 7927 | B87: 1 | C87: f | D87: 13050510 | E87: 2 | F87: 42760 | G87: 28320 | H87: 51759 | I87: 1 | J87: RC CLIENTES CREDITO | K87: 2 | L87: 2200 | M87: 0 | O87: 90 | P87: 1 | Y87: 1 | Z87: 1 | AA87: 1 | AB87: 1 | AC87: 43511.928 | AD87: 43511.928
A88: 7928 | B88: 1 | C88: f | D88: 13050510 | E88: 2 | F88: 42760 | G88: 28320 | H88: 51758 | I88: 1 | J88: RC CLIENTES CREDITO | K88: 2 | L88: 15150 | M88: 0 | O88: 90 | P88: 1 | Y88: 1 | Z88: 1 | AA88: 1 | AB88: 1 | AC88: 43511.928 | AD88: 43511.928
A89: 7929 | B89: 1 | C89: f | D89: 13050510 | E89: 2 | F89: 42760 | G89: 28320 | H89: 51751 | I89: 1 | J89: RC CLIENTES CREDITO | K89: 2 | L89: 136081 | M89: 0 | O89: 90 | P89: 1 | Y89: 1 | Z89: 1 | AA89: 1 | AB89: 1 | AC89: 43511.928 | AD89: 43511.928
A90: 7930 | B90: 1 | C90: f | D90: 13050510 | E90: 2 | F90: 42760 | G90: 28320 | H90: 51750 | I90: 1 | J90: RC CLIENTES CREDITO | K90: 2 | L90: 5500 | M90: 0 | O90: 90 | P90: 1 | Y90: 1 | Z90: 1 | AA90: 1 | AB90: 1 | AC90: 43511.928 | AD90: 43511.928
A91: 7931 | B91: 1 | C91: f | D91: 11050501 | E91: 2 | F91: 42760 | G91: 28320 | H91: 0 | J91: VLR TOTAL DOC 000028320 | K91: 1 | L91: 176531 | M91: 0 | O91: 90 | P91: 1 | Y91: 1 | Z91: 1 | AA91: 1 | AB91: 1 | AC91: 43511.928 | AD91: 43511.928
A92: 7932 | B92: 1 | C92: f | D92: 13050510 | E92: 2 | F92: 42760 | G92: 28321 | H92: 51786 | I92: 42763194 | J92: RC CLIENTES CREDITO | K92: 2 | L92: 26270 | M92: 0 | O92: 90 | P92: 0 | Y92: 1 | Z92: 1 | AA92: 1 | AB92: 1 | AC92: 43511.928 | AD92: 43511.928
A93: 7933 | B93: 1 | C93: f | D93: 11050501 | E93: 2 | F93: 42760 | G93: 28321 | H93: 0 | J93: VLR TOTAL DOC 000028321 | K93: 1 | L93: 26270 | M93: 0 | O93: 90 | P93: 0 | Y93: 1 | Z93: 1 | AA93: 1 | AB93: 1 | AC93: 43511.928 | AD93: 43511.928
A94: 7934 | B94: 1 | C94: f | D94: 13050510 | E94: 2 | F94: 42760 | G94: 28322 | H94: 51772 | I94: 70165691 | J94: RC CLIENTES CREDITO | K94: 2 | L94: 140169 | M94: 0 | O94: 90 | P94: 0 | Y94: 1 | Z94: 1 | AA94: 1 | AB94: 1 | AC94: 43511.928 | AD94: 43511.928
A95: 7935 | B95: 1 | C95: f | D95: 11050501 | E95: 2 | F95: 42760 | G95: 28322 | H95: 0 | J95: VLR TOTAL DOC 000028322 | K95: 1 | L95: 140169 | M95: 0 | O95: 90 | P95: 0 | Y95: 1 | Z95: 1 | AA95: 1 | AB95: 1 | AC95: 43511.928 | AD95: 43511.928
A96: 7936 | B96: 1 | C96: f | D96: 13050510 | E96: 2 | F96: 42760 | G96: 28323 | H96: 51771 | I96: 70041563 | J96: RC CLIENTES CREDITO | K96: 2 | L96: 36036 | M96: 0 | O96: 90 | P96: 8 | Y96: 1 | Z96: 1 | AA96: 1 | AB96: 1 | AC96: 43511.928 | AD96: 43511.928
A97: 7937 | B97: 1 | C97: f | D97: 11050501 | E97: 2 | F97: 42760 | G97: 28323 | H97: 0 | J97: VLR TOTAL DOC 000028323 | K97: 1 | L97: 36036 | M97: 0 | O97: 90 | P97: 8 | Y97: 1 | Z97: 1 | AA97: 1 | AB97: 1 | AC97: 43511.928 | AD97: 43511.928
A98: 7938 | B98: 1 | C98: f | D98: 13050510 | E98: 2 | F98: 42760 | G98: 28324 | H98: 51768 | I98: 32318895 | J98: RC CLIENTES CREDITO | K98: 2 | L98: 30856 | M98: 0 | O98: 90 | P98: 0 | Y98: 1 | Z98: 1 | AA98: 1 | AB98: 1 | AC98: 43511.928 | AD98: 43511.928
A99: 7939 | B99: 1 | C99: f | D99: 11050501 | E99: 2 | F99: 42760 | G99: 28324 | H99: 0 | J99: VLR TOTAL DOC 000028324 | K99: 1 | L99: 30856 | M99: 0 | O99: 90 | P99: 0 | Y99: 1 | Z99: 1 | AA99: 1 | AB99: 1 | AC99: 43511.928 | AD99: 43511.928
A100: 7940 | B100: 1 | C100: f | D100: 13050510 | E100: 2 | F100: 42760 | G100: 28325 | H100: 51767 | I100: 22057509 | J100: RC CLIENTES CREDITO | K100: 2 | L100: 146584 | M100: 0 | O100: 90 | P100: 0 | Y100: 1 | Z100: 1 | AA100: 1 | AB100: 1 | AC100: 43511.928 | AD100: 43511.928
...

Sheet PRIMER DIGITO
A1: REGISTRO | B1: VALOR | C1: VAMOS A EXTRAER EL PRIMER DIGITO | J1: DESVIACION ABSOLUTA MEDIA (MAD)
A2: 1 | B2: 153800 | C2: =_xlfn.NUMBERVALUE(MID(B2,1,1)) -> 1 | I2: VALOR ABSOLUTO (FRECUENCIA OBSERVADA - FRECUENCIA ESPERADA)
A3: =+A2+1 -> 2 | B3: 9000 | C3: =_xlfn.NUMBERVALUE(MID(B3,1,1)) -> 9 | D3: VAMOS A VER LA FRECUENCIA EN QUE SE REPITE CADA NUMERO | I3: N = 9
A4: =+A3+1 -> 3 | B4: 37800 | C4: =_xlfn.NUMBERVALUE(MID(B4,1,1)) -> 3 | E4: ACUMULADA | F4: FRECUENCIA | G4: % OBSERVADO | H4: BENFORD PRIMER DIGITO | J4: VARIACION | K4: VALOR ABSOLUTO
A5: =+A4+1 -> 4 | B5: 100000 | C5: =_xlfn.NUMBERVALUE(MID(B5,1,1)) -> 1 | D5: 1 | E5: =FREQUENCY($C$2:$C$9657,D5) -> 3317 | F5: =+E5 -> 3317 | G5: =+F5/$F$15 -> 0.34351698 | H5: 0.30103 | J5: =+(G5-H5) -> 0.042486989 | K5: =ABS(J5) -> 0.042486989
A6: =+A5+1 -> 5 | B6: 25000 | C6: =_xlfn.NUMBERVALUE(MID(B6,1,1)) -> 2 | D6: 2 | E6: =FREQUENCY($C$2:$C$9657,D6) -> 5069 | F6: =+E6-E5 -> 1752 | G6: =+F6/$F$15 -> 0.18144159 | H6: 0.17609126 | J6: =+(G6-H6) -> 0.0053503317 | K6: =ABS(J6) -> 0.0053503317
A7: =+A6+1 -> 6 | B7: 182900 | C7: =_xlfn.NUMBERVALUE(MID(B7,1,1)) -> 1 | D7: 3 | E7: =FREQUENCY($C$2:$C$9657,D7) -> 6240 | F7: =+E7-E6 -> 1171 | G7: =+F7/$F$15 -> 0.12127175 | H7: 0.12493874 | J7: =+(G7-H7) -> -0.0036669885 | K7: =ABS(J7) -> 0.0036669885
A8: =+A7+1 -> 7 | B8: 157900 | C8: =_xlfn.NUMBERVALUE(MID(B8,1,1)) -> 1 | D8: 4 | E8: =FREQUENCY($C$2:$C$9657,D8) -> 7061 | F8: =+E8-E7 -> 821 | G8: =+F8/$F$15 -> 0.085024855 | H8: 0.096910013 | J8: =+(G8-H8) -> -0.011885158 | K8: =ABS(J8) -> 0.011885158 | L8: MAD | M8: =+K15/9 -> 0.010630516
A9: =+A8+1 -> 8 | B9: 25000 | C9: =_xlfn.NUMBERVALUE(MID(B9,1,1)) -> 2 | D9: 5 | E9: =FREQUENCY($C$2:$C$9657,D9) -> 7790 | F9: =+E9-E8 -> 729 | G9: =+F9/$F$15 -> 0.0754971 | H9: 0.079181246 | J9: =+(G9-H9) -> -0.0036841458 | K9: =ABS(J9) -> 0.0036841458
A10: =+A9+1 -> 9 | B10: 181550 | C10: =_xlfn.NUMBERVALUE(MID(B10,1,1)) -> 1 | D10: 6 | E10: =FREQUENCY($C$2:$C$9657,D10) -> 8310 | F10: =+E10-E9 -> 520 | G10: =+F10/$F$15 -> 0.053852527 | H10: 0.06694679 | J10: =+(G10-H10) -> -0.013094263 | K10: =ABS(J10) -> 0.013094263
A11: =+A10+1 -> 10 | B11: 6000 | C11: =_xlfn.NUMBERVALUE(MID(B11,1,1)) -> 6 | D11: 7 | E11: =FREQUENCY($C$2:$C$9657,D11) -> 8808 | F11: =+E11-E10 -> 498 | G11: =+F11/$F$15 -> 0.051574151 | H11: 0.057991947 | J11: =+(G11-H11) -> -0.0064177962 | K11: =ABS(J11) -> 0.0064177962
A12: =+A11+1 -> 11 | B12: 175550 | C12: =_xlfn.NUMBERVALUE(MID(B12,1,1)) -> 1 | D12: 8 | E12: =FREQUENCY($C$2:$C$9657,D12) -> 9259 | F12: =+E12-E11 -> 451 | G12: =+F12/$F$15 -> 0.046706711 | H12: 0.051152522 | J12: =+(G12-H12) -> -0.0044458116 | K12: =ABS(J12) -> 0.0044458116
A13: =+A12+1 -> 12 | B13: 75500 | C13: =_xlfn.NUMBERVALUE(MID(B13,1,1)) -> 7 | D13: 9 | E13: =FREQUENCY($C$2:$C$9657,D13) -> 9656 | F13: =+E13-E12 -> 397 | G13: =+F13/$F$15 -> 0.041114333 | H13: 0.045757491 | J13: =+(G13-H13) -> -0.0046431575 | K13: =ABS(J13) -> 0.0046431575
A14: =+A13+1 -> 13 | B14: 1000 | C14: =_xlfn.NUMBERVALUE(MID(B14,1,1)) -> 1
A15: =+A14+1 -> 14 | B15: 74500 | C15: =_xlfn.NUMBERVALUE(MID(B15,1,1)) -> 7 | E15: TOTAL | F15: =SUM(F5:F14) -> 9656 | G15: =SUM(G5:G14) -> 1 | H15: =SUM(H5:H14) -> 1 | K15: =SUM(K5:K14) -> 0.095674641
A16: =+A15+1 -> 15 | B16: 184610 | C16: =_xlfn.NUMBERVALUE(MID(B16,1,1)) -> 1
A17: =+A16+1 -> 16 | B17: 184610 | C17: =_xlfn.NUMBERVALUE(MID(B17,1,1)) -> 1
A18: =+A17+1 -> 17 | B18: 128000 | C18: =_xlfn.NUMBERVALUE(MID(B18,1,1)) -> 1 | F18: ESTA MAD LA COMPARAMOS CON LA TABLA PARAEL PRIMER DIGITO
A19: =+A18+1 -> 18 | B19: 128000 | C19: =_xlfn.NUMBERVALUE(MID(B19,1,1)) -> 1
A20: =+A19+1 -> 19 | B20: 370370 | C20: =_xlfn.NUMBERVALUE(MID(B20,1,1)) -> 3
A21: =+A20+1 -> 20 | B21: 324485 | C21: =_xlfn.NUMBERVALUE(MID(B21,1,1)) -> 3
A22: =+A21+1 -> 21 | B22: 45885 | C22: =_xlfn.NUMBERVALUE(MID(B22,1,1)) -> 4
A23: =+A22+1 -> 22 | B23: 352295 | C23: =_xlfn.NUMBERVALUE(MID(B23,1,1)) -> 3
A24: =+A23+1 -> 23 | B24: 335095 | C24: =_xlfn.NUMBERVALUE(MID(B24,1,1)) -> 3
A25: =+A24+1 -> 24 | B25: 1800 | C25: =_xlfn.NUMBERVALUE(MID(B25,1,1)) -> 1
A26: =+A25+1 -> 25 | B26: 7000 | C26: =_xlfn.NUMBERVALUE(MID(B26,1,1)) -> 7 | E26: EN ESTE CASO NOS DA 0.01063052 QUE VIENDOLO EN LA TABA ES CONFORMIDAD ACEPTABLE
A27: =+A26+1 -> 26 | B27: 8375 | C27: =_xlfn.NUMBERVALUE(MID(B27,1,1)) -> 8
A28: =+A27+1 -> 27 | B28: 25 | C28: =_xlfn.NUMBERVALUE(MID(B28,1,1)) -> 2
A29: =+A28+1 -> 28 | B29: 182350 | C29: =_xlfn.NUMBERVALUE(MID(B29,1,1)) -> 1 | J29: CHI CUADRADO Y CHI CUADRADO CRITICO
A30: =+A29+1 -> 29 | B30: 157350 | C30: =_xlfn.NUMBERVALUE(MID(B30,1,1)) -> 1 | I30: SUMATORIA DE VALOR OBSERVADO MENOS VALOR ESPERADO ELEVADO AL CUADRADO
A31: =+A30+1 -> 30 | B31: 25000 | C31: =_xlfn.NUMBERVALUE(MID(B31,1,1)) -> 2 | I31: VALOR ESPERADO
A32: =+A31+1 -> 31 | B32: 126600 | C32: =_xlfn.NUMBERVALUE(MID(B32,1,1)) -> 1 | D32: VAMOS A VER LA FRECUENCIA EN QUE SE REPITE CADA NUMERO | J32: VALOR ESPERADO BENFORD = TOTAL DATOSPOR % BENFORD
B33: 101600 | C33: =_xlfn.NUMBERVALUE(MID(B33,1,1)) -> 1 | E33: ACUMULADA | F33: FRECUENCIA | G33: % OBSERVADO | H33: BENFORD UN DIGITO | K33: VALOR OBSERVADO MENOS VALOR ESPERADO ELEVADO AL CUADRADO
A34: =+A33+1 -> 1 | B34: 25000 | C34: =_xlfn.NUMBERVALUE(MID(B34,1,1)) -> 2 | D34: 1 | E34: =FREQUENCY($C$2:$C$9657,D34) -> 3317 | F34: =+E34 -> 3317 | G34: =+F34/$F$15 -> 0.34351698 | H34: 0.30103 | J34: =+$F$44*H34 -> 2906.7456 | K34: =+((F34-J34)^2)/J34 -> 57.902776
A35: =+A34+1 -> 2 | B35: 153300 | C35: =_xlfn.NUMBERVALUE(MID(B35,1,1)) -> 1 | D35: 2 | E35: =FREQUENCY($C$2:$C$9657,D35) -> 5069 | F35: =+E35-E34 -> 1752 | G35: =+F35/$F$15 -> 0.18144159 | H35: 0.17609126 | J35: =+$F$44*H35 -> 1700.3372 | K35: =+((F35-J35)^2)/J35 -> 1.5697152
A36: =+A35+1 -> 3 | B36: 153300 | C36: =_xlfn.NUMBERVALUE(MID(B36,1,1)) -> 1 | D36: 3 | E36: =FREQUENCY($C$2:$C$9657,D36) -> 6240 | F36: =+E36-E35 -> 1171 | G36: =+F36/$F$15 -> 0.12127175 | H36: 0.12493874 | J36: =+$F$44*H36 -> 1206.4084 | K36: =+((F36-J36)^2)/J36 -> 1.0392481
A37: =+A36+1 -> 4 | B37: 217300 | C37: =_xlfn.NUMBERVALUE(MID(B37,1,1)) -> 2 | D37: 4 | E37: =FREQUENCY($C$2:$C$9657,D37) -> 7061 | F37: =+E37-E36 -> 821 | G37: =+F37/$F$15 -> 0.085024855 | H37: 0.096910013 | J37: =+$F$44*H37 -> 935.76309 | K37: =+((F37-J37)^2)/J37 -> 14.07468
A38: =+A37+1 -> 5 | B38: 217300 | C38: =_xlfn.NUMBERVALUE(MID(B38,1,1)) -> 2 | D38: 5 | E38: =FREQUENCY($C$2:$C$9657,D38) -> 7790 | F38: =+E38-E37 -> 729 | G38: =+F38/$F$15 -> 0.0754971 | H38: 0.079181246 | J38: =+$F$44*H38 -> 764.57411 | K38: =+((F38-J38)^2)/J38 -> 1.6551926
A39: =+A38+1 -> 6 | B39: 152200 | C39: =_xlfn.NUMBERVALUE(MID(B39,1,1)) -> 1 | D39: 6 | E39: =FREQUENCY($C$2:$C$9657,D39) -> 8310 | F39: =+E39-E38 -> 520 | G39: =+F39/$F$15 -> 0.053852527 | H39: 0.06694679 | J39: =+$F$44*H39 -> 646.4382 | K39: =+((F39-J39)^2)/J39 -> 24.730312
A40: =+A39+1 -> 7 | B40: 147900 | C40: =_xlfn.NUMBERVALUE(MID(B40,1,1)) -> 1 | D40: 7 | E40: =FREQUENCY($C$2:$C$9657,D40) -> 8808 | F40: =+E40-E39 -> 498 | G40: =+F40/$F$15 -> 0.051574151 | H40: 0.057991947 | J40: =+$F$44*H40 -> 559.97024 | K40: =+((F40-J40)^2)/J40 -> 6.858062
A41: =+A40+1 -> 8 | B41: 4300 | C41: =_xlfn.NUMBERVALUE(MID(B41,1,1)) -> 4 | D41: 8 | E41: =FREQUENCY($C$2:$C$9657,D41) -> 9259 | F41: =+E41-E40 -> 451 | G41: =+F41/$F$15 -> 0.046706711 | H41: 0.051152522 | J41: =+$F$44*H41 -> 493.92876 | K41: =+((F41-J41)^2)/J41 -> 3.7310607
A42: =+A41+1 -> 9 | B42: 183100 | C42: =_xlfn.NUMBERVALUE(MID(B42,1,1)) -> 1 | D42: 9 | E42: =FREQUENCY($C$2:$C$9657,D42) -> 9656 | F42: =+E42-E41 -> 397 | G42: =+F42/$F$15 -> 0.041114333 | H42: 0.045757491 | J42: =+$F$44*H42 -> 441.83433 | K42: =+((F42-J42)^2)/J42 -> 4.5494814
A43: =+A42+1 -> 10 | B43: 183100 | C43: =_xlfn.NUMBERVALUE(MID(B43,1,1)) -> 1
A44: =+A43+1 -> 11 | B44: 257650 | C44: =_xlfn.NUMBERVALUE(MID(B44,1,1)) -> 2 | E44: TOTAL | F44: =SUM(F34:F43) -> 9656 | G44: =SUM(G34:G43) -> 1 | H44: =SUM(H34:H43) -> 1 | J44: =SUM(J34:J43) -> 9656 | K44: =SUM(K34:K43) -> 116.11053
A45: =+A44+1 -> 12 | B45: 257100 | C45: =_xlfn.NUMBERVALUE(MID(B45,1,1)) -> 2
A46: =+A45+1 -> 13 | B46: 550 | C46: =_xlfn.NUMBERVALUE(MID(B46,1,1)) -> 5
A47: =+A46+1 -> 14 | B47: 214100 | C47: =_xlfn.NUMBERVALUE(MID(B47,1,1)) -> 2 | E47: ESTE VALOR LO COMPARO CON 15.5073 QUE ES VALOR DEL CHI CUADRADO CRITICO PARA UN DIGITO
A48: =+A47+1 -> 15 | B48: 214100 | C48: =_xlfn.NUMBERVALUE(MID(B48,1,1)) -> 2 | E48: QUE SALE DE LA TABLA CHI CUADRADO CON UN 95% DE PROBABILIDAD Y ES FIJO
A49: =+A48+1 -> 16 | B49: 316315 | C49: =_xlfn.NUMBERVALUE(MID(B49,1,1)) -> 3
A50: =+A49+1 -> 17 | B50: 311565 | C50: =_xlfn.NUMBERVALUE(MID(B50,1,1)) -> 3
A51: =+A50+1 -> 18 | B51: 4750 | C51: =_xlfn.NUMBERVALUE(MID(B51,1,1)) -> 4 | E51: SI EL CHI CUADRADO DA MAYOR QUE ESTE ULTIMO DATO, LOS DATOS DEL MOVIMIENTO SON
A52: =+A51+1 -> 19 | B52: 1338541 | C52: =_xlfn.NUMBERVALUE(MID(B52,1,1)) -> 1 | E52: CONFIABLES
A53: =+A52+1 -> 20 | B53: 116633 | C53: =_xlfn.NUMBERVALUE(MID(B53,1,1)) -> 1
A54: =+A53+1 -> 21 | B54: 450000 | C54: =_xlfn.NUMBERVALUE(MID(B54,1,1)) -> 4 | E54: ES DECIR | F54: 116.11053 | G54: MAYOR QUE | H54: 15.5073 | I54: RESULTADO | J54: CONFIABLE
A55: =+A54+1 -> 22 | B55: 673178 | C55: =_xlfn.NUMBERVALUE(MID(B55,1,1)) -> 6
A56: =+A55+1 -> 23 | B56: 12000 | C56: =_xlfn.NUMBERVALUE(MID(B56,1,1)) -> 1
A57: =+A56+1 -> 24 | B57: 27000 | C57: =_xlfn.NUMBERVALUE(MID(B57,1,1)) -> 2
A58: =+A57+1 -> 25 | B58: 43740 | C58: =_xlfn.NUMBERVALUE(MID(B58,1,1)) -> 4
A59: =+A58+1 -> 26 | B59: 15990 | C59: =_xlfn.NUMBERVALUE(MID(B59,1,1)) -> 1
A60: =+A59+1 -> 27 | B60: 3777849 | C60: =_xlfn.NUMBERVALUE(MID(B60,1,1)) -> 3
A61: =+A60+1 -> 28 | B61: 841508 | C61: =_xlfn.NUMBERVALUE(MID(B61,1,1)) -> 8
A62: =+A61+1 -> 29 | B62: 31750 | C62: =_xlfn.NUMBERVALUE(MID(B62,1,1)) -> 3
A63: =+A62+1 -> 30 | B63: 398615 | C63: =_xlfn.NUMBERVALUE(MID(B63,1,1)) -> 3
A64: =+A63+1 -> 31 | B64: 1508000 | C64: =_xlfn.NUMBERVALUE(MID(B64,1,1)) -> 1
A65: =+A64+1 -> 32 | B65: 160817 | C65: =_xlfn.NUMBERVALUE(MID(B65,1,1)) -> 1
A66: =+A65+1 -> 33 | B66: 130100 | C66: =_xlfn.NUMBERVALUE(MID(B66,1,1)) -> 1
... A9657: =+A9656+1 -> 9624 | B9657: 366111 | C9657: =_xlfn.NUMBERVALUE(MID(B9657,1,1)) -> 3

Sheet SEGUNDO DIGITO
A1: REGISTRO | B1: VALOR | C1: VAMOS A EXTRAER EL SEGUNDO DIGITO | J1: DESVIACION ABSOLUTA MEDIA (MAD)
A2: 1 | B2: 153800 | C2: =_xlfn.NUMBERVALUE(MID(B2,2,1)) -> 5 | I2: VALOR ABSOLUTO (FRECUENCIA OBSERVADA - FRECUENCIA ESPERADA)
A3: 2 | B3: 9000 | C3: =_xlfn.NUMBERVALUE(MID(B3,2,1)) -> 0 | D3: VAMOS A VER LA FRECUENCIA EN QUE SE REPITE CADA NUMERO | I3: N = 10
A4: 3 | B4: 37800 | C4: =_xlfn.NUMBERVALUE(MID(B4,2,1)) -> 7 | E4: ACUMULADA | F4: FRECUENCIA | G4: % OBSERVADO | H4: BENFORD SEGUNDO DIGITO | J4: VARIACION | K4: VALOR ABSOLUTO
A5: 4 | B5: 100000 | C5: =_xlfn.NUMBERVALUE(MID(B5,2,1)) -> 0 | D5: 0 | E5: =FREQUENCY($C$2:$C$9657,D5) -> #VALUE! | F5: =+E5 -> #VALUE! | G5: =+F5/$F$16 -> #VALUE! | H5: 0.11967927 | J5: =+(G5-H5) -> #VALUE! | K5: =ABS(J5) -> #VALUE!
A6: 5 | B6: 25000 | C6: =_xlfn.NUMBERVALUE(MID(B6,2,1)) -> 5 | D6: 1 | E6: =FREQUENCY($C$2:$C$9657,D6) -> #VALUE! | F6: =+E6-F5 -> #VALUE! | G6: =+F6/$F$16 -> #VALUE! | H6: 0.1138901 | J6: =+(G6-H6) -> #VALUE! | K6: =ABS(J6) -> #VALUE!
A7: 6 | B7: 182900 | C7: =_xlfn.NUMBERVALUE(MID(B7,2,1)) -> 8 | D7: 2 | E7: =FREQUENCY($C$2:$C$9657,D7) -> #VALUE! | F7: =+E7-E6 -> #VALUE! | G7: =+F7/$F$16 -> #VALUE! | H7: 0.1088215 | J7: =+(G7-H7) -> #VALUE! | K7: =ABS(J7) -> #VALUE!
A8: 7 | B8: 157900 | C8: =_xlfn.NUMBERVALUE(MID(B8,2,1)) -> 5 | D8: 3 | E8: =FREQUENCY($C$2:$C$9657,D8) -> #VALUE! | F8: =+E8-E7 -> #VALUE! | G8: =+F8/$F$16 -> #VALUE! | H8: 0.10432956 | J8: =+(G8-H8) -> #VALUE! | K8: =ABS(J8) -> #VALUE!
A9: 8 | B9: 25000 | C9: =_xlfn.NUMBERVALUE(MID(B9,2,1)) -> 5 | D9: 4 | E9: =FREQUENCY($C$2:$C$9657,D9) -> #VALUE! | F9: =+E9-E8 -> #VALUE! | G9: =+F9/$F$16 -> #VALUE! | H9: 0.1003082 | J9: =+(G9-H9) -> #VALUE! | K9: =ABS(J9) -> #VALUE! | L9: MAD | M9: =+K16/10 -> #VALUE!
A10: 9 | B10: 181550 | C10: =_xlfn.NUMBERVALUE(MID(B10,2,1)) -> 8 | D10: 5 | E10: =FREQUENCY($C$2:$C$9657,D10) -> #VALUE! | F10: =+E10-E9 -> #VALUE! | G10: =+F10/$F$16 -> #VALUE! | H10: 0.096677236 | J10: =+(G10-H10) -> #VALUE! | K10: =ABS(J10) -> #VALUE!
A11: 10 | B11: 6000 | C11: =_xlfn.NUMBERVALUE(MID(B11,2,1)) -> 0 | D11: 6 | E11: =FREQUENCY($C$2:$C$9657,D11) -> #VALUE! | F11: =+E11-E10 -> #VALUE! | G11: =+F11/$F$16 -> #VALUE! | H11: 0.093374736 | J11: =+(G11-H11) -> #VALUE! | K11: =ABS(J11) -> #VALUE!
A12: 11 | B12: 175550 | C12: =_xlfn.NUMBERVALUE(MID(B12,2,1)) -> 7 | D12: 7 | E12: =FREQUENCY($C$2:$C$9657,D12) -> #VALUE! | F12: =+E12-E11 -> #VALUE! | G12: =+F12/$F$16 -> #VALUE! | H12: 0.090351989 | J12: =+(G12-H12) -> #VALUE! | K12: =ABS(J12) -> #VALUE!
A13: 12 | B13: 75500 | C13: =_xlfn.NUMBERVALUE(MID(B13,2,1)) -> 5 | D13: 8 | E13: =FREQUENCY($C$2:$C$9657,D13) -> #VALUE! | F13: =+E13-E12 -> #VALUE! | G13: =+F13/$F$16 -> #VALUE! | H13: 0.087570054 | J13: =+(G13-H13) -> #VALUE! | K13: =ABS(J13) -> #VALUE!
A14: 13 | B14: 1000 | C14: =_xlfn.NUMBERVALUE(MID(B14,2,1)) -> 0 | D14: 9 | E14: =FREQUENCY($C$2:$C$9657,D14) -> #VALUE! | F14: =+E14-E13 -> #VALUE! | G14: =+F14/$F$16 -> #VALUE! | H14: 0.084997352 | J14: =+(G14-H14) -> #VALUE! | K14: =ABS(J14) -> #VALUE!
A15: 14 | B15: 74500 | C15: =_xlfn.NUMBERVALUE(MID(B15,2,1)) -> 4
A16: 15 | B16: 184610 | C16: =_xlfn.NUMBERVALUE(MID(B16,2,1)) -> 8 | E16: TOTAL | F16: =SUM(F5:F15) -> #VALUE! | G16: =SUM(G5:G15) -> #VALUE! | H16: =SUM(H5:H14) -> 1 | K16: =SUM(K5:K15) -> #VALUE!
A17: 16 | B17: 184610 | C17: =_xlfn.NUMBERVALUE(MID(B17,2,1)) -> 8
A18: 17 | B18: 128000 | C18: =_xlfn.NUMBERVALUE(MID(B18,2,1)) -> 2
A19: 18 | B19: 128000 | C19: =_xlfn.NUMBERVALUE(MID(B19,2,1)) -> 2 | G19: ESTA MAD LA COMPARAMOS CON LA TABLA PARA EL SEGUNDO DIGITO
A20: 19 | B20: 370370 | C20: =_xlfn.NUMBERVALUE(MID(B20,2,1)) -> 7
A21: 20 | B21: 324485 | C21: =_xlfn.NUMBERVALUE(MID(B21,2,1)) -> 2
A22: 21 | B22: 45885 | C22: =_xlfn.NUMBERVALUE(MID(B22,2,1)) -> 5
A23: 22 | B23: 352295 | C23: =_xlfn.NUMBERVALUE(MID(B23,2,1)) -> 5
A24: 23 | B24: 335095 | C24: =_xlfn.NUMBERVALUE(MID(B24,2,1)) -> 3
A25: 24 | B25: 1800 | C25: =_xlfn.NUMBERVALUE(MID(B25,2,1)) -> 8
A26: 25 | B26: 7000 | C26: =_xlfn.NUMBERVALUE(MID(B26,2,1)) -> 0
A27: 26 | B27: 8375 | C27: =_xlfn.NUMBERVALUE(MID(B27,2,1)) -> 3 | E27: EN ESTE CASO NOS DA 0.00686873 QUE VIENDOLO EN LA TABA ES CONFORMIDAD CUASI- PERFECTA
A28: 27 | B28: 25 | C28: =_xlfn.NUMBERVALUE(MID(B28,2,1)) -> 5
A29: 28 | B29: 182350 | C29: =_xlfn.NUMBERVALUE(MID(B29,2,1)) -> 8
A30: 29 | B30: 157350 | C30: =_xlfn.NUMBERVALUE(MID(B30,2,1)) -> 5 | J30: CHI CUADRADO Y CHI CUADRADO CRITICO
A31: 30 | B31: 25000 | C31: =_xlfn.NUMBERVALUE(MID(B31,2,1)) -> 5 | I31: SUMATORIA DE VALOR OBSERVADO MENOS VALOR ESPERADO ELEVADO AL CUADRADO
A32: 31 | B32: 126600 | C32: =_xlfn.NUMBERVALUE(MID(B32,2,1)) -> 2 | I32: VALOR ESPERADO
A33: 32 | B33: 101600 | C33: =_xlfn.NUMBERVALUE(MID(B33,2,1)) -> 0 | D33: VAMOS A VER LA FRECUENCIA EN QUE SE REPITE CADA NUMERO | J33: VALOR ESPERADO BENFORD = TOTAL DATOS POR % BENFORD
A34: 33 | B34: 25000 | C34: =_xlfn.NUMBERVALUE(MID(B34,2,1)) -> 5 | E34: ACUMULADA | F34: FRECUENCIA | G34: % OBSERVADO | H34: BENFORD UN DIGITO | K34: VALOR OBSERVADO MENOS VALOR ESPERADO ELEVADO AL CUADRADO
A35: 34 | B35: 153300 | C35: =_xlfn.NUMBERVALUE(MID(B35,2,1)) -> 5 | D35: 0 | E35: =FREQUENCY($C$2:$C$9657,D35) -> #VALUE! | F35: =+E35 -> #VALUE! | G35: =+F35/$F$16 -> #VALUE! | H35: 0.11967927 | J35: =+$F$46*H35 -> #VALUE! | K35: =+((F35-J35)^2)/J35 -> #VALUE!
A36: 35 | B36: 153300 | C36: =_xlfn.NUMBERVALUE(MID(B36,2,1)) -> 5 | D36: 1 | E36: =FREQUENCY($C$2:$C$9657,D36) -> #VALUE! | F36: =+E36-E35 -> #VALUE! | G36: =+F36/$F$16 -> #VALUE! | H36: 0.1138901 | J36: =+$F$46*H36 -> #VALUE! | K36: =+((F36-J36)^2)/J36 -> #VALUE!
A37: 36 | B37: 217300 | C37: =_xlfn.NUMBERVALUE(MID(B37,2,1)) -> 1 | D37: 2 | E37: =FREQUENCY($C$2:$C$9657,D37) -> #VALUE! | F37: =+E37-E36 -> #VALUE! | G37: =+F37/$F$16 -> #VALUE! | H37: 0.1088215 | J37: =+$F$46*H37 -> #VALUE! | K37: =+((F37-J37)^2)/J37 -> #VALUE!
A38: 37 | B38: 217300 | C38: =_xlfn.NUMBERVALUE(MID(B38,2,1)) -> 1 | D38: 3 | E38: =FREQUENCY($C$2:$C$9657,D38) -> #VALUE! | F38: =+E38-E37 -> #VALUE! | G38: =+F38/$F$16 -> #VALUE! | H38: 0.10432956 | J38: =+$F$46*H38 -> #VALUE! | K38: =+((F38-J38)^2)/J38 -> #VALUE!
A39: 38 | B39: 152200 | C39: =_xlfn.NUMBERVALUE(MID(B39,2,1)) -> 5 | D39: 4 | E39: =FREQUENCY($C$2:$C$9657,D39) -> #VALUE! | F39: =+E39-E38 -> #VALUE! | G39: =+F39/$F$16 -> #VALUE! | H39: 0.1003082 | J39: =+$F$46*H39 -> #VALUE! | K39: =+((F39-J39)^2)/J39 -> #VALUE!
A40: 39 | B40: 147900 | C40: =_xlfn.NUMBERVALUE(MID(B40,2,1)) -> 4 | D40: 5 | E40: =FREQUENCY($C$2:$C$9657,D40) -> #VALUE! | F40: =+E40-E39 -> #VALUE! | G40: =+F40/$F$16 -> #VALUE! | H40: 0.096677236 | J40: =+$F$46*H40 -> #VALUE! | K40: =+((F40-J40)^2)/J40 -> #VALUE!
A41: 40 | B41: 4300 | C41: =_xlfn.NUMBERVALUE(MID(B41,2,1)) -> 3 | D41: 6 | E41: =FREQUENCY($C$2:$C$9657,D41) -> #VALUE! | F41: =+E41-E40 -> #VALUE! | G41: =+F41/$F$16 -> #VALUE! | H41: 0.093374736 | J41: =+$F$46*H41 -> #VALUE! | K41: =+((F41-J41)^2)/J41 -> #VALUE!
A42: 41 | B42: 183100 | C42: =_xlfn.NUMBERVALUE(MID(B42,2,1)) -> 8 | D42: 7 | E42: =FREQUENCY($C$2:$C$9657,D42) -> #VALUE! | F42: =+E42-E41 -> #VALUE! | G42: =+F42/$F$16 -> #VALUE! | H42: 0.090351989 | J42: =+$F$46*H42 -> #VALUE! | K42: =+((F42-J42)^2)/J42 -> #VALUE!
A43: 42 | B43: 183100 | C43: =_xlfn.NUMBERVALUE(MID(B43,2,1)) -> 8 | D43: 8 | E43: =FREQUENCY($C$2:$C$9657,D43) -> #VALUE! | F43: =+E43-E42 -> #VALUE! | G43: =+F43/$F$16 -> #VALUE! | H43: 0.087570054 | J43: =+$F$46*H43 -> #VALUE! | K43: =+((F43-J43)^2)/J43 -> #VALUE!
A44: 43 | B44: 257650 | C44: =_xlfn.NUMBERVALUE(MID(B44,2,1)) -> 5 | D44: 9 | E44: =FREQUENCY($C$2:$C$9657,D44) -> #VALUE! | F44: =+E44-E43 -> #VALUE! | G44: =+F44/$F$16 -> #VALUE! | H44: 0.084997352 | J44: =+$F$46*H44 -> #VALUE! | K44: =+((F44-J44)^2)/J44 -> #VALUE!
A45: 44 | B45: 257100 | C45: =_xlfn.NUMBERVALUE(MID(B45,2,1)) -> 5
A46: 45 | B46: 550 | C46: =_xlfn.NUMBERVALUE(MID(B46,2,1)) -> 5 | E46: TOTAL | F46: =SUM(F35:F45) -> #VALUE! | G46: =SUM(G35:G45) -> #VALUE! | H46: =SUM(H35:H45) -> 1 | J46: =SUM(J35:J45) -> #VALUE! | K46: =SUM(K35:K45) -> #VALUE!
A47: 46 | B47: 214100 | C47: =_xlfn.NUMBERVALUE(MID(B47,2,1)) -> 1
A48: 47 | B48: 214100 | C48: =_xlfn.NUMBERVALUE(MID(B48,2,1)) -> 1
A49: 48 | B49: 316315 | C49: =_xlfn.NUMBERVALUE(MID(B49,2,1)) -> 1 | E49: ESTE VALOR LO COMPARO CON 15.5073 QUE ES VALOR DEL CHI CUADRADO CRITICO PARA UN DIGITO
A50: 49 | B50: 311565 | C50: =_xlfn.NUMBERVALUE(MID(B50,2,1)) -> 1 | E50: QUE SALE DE LA TABLA CHI CUADRADO CON UN 95% DE PROBABILIDAD Y ES FIJO
A51: 50 | B51: 4750 | C51: =_xlfn.NUMBERVALUE(MID(B51,2,1)) -> 7
A52: 51 | B52: 1338541 | C52: =_xlfn.NUMBERVALUE(MID(B52,2,1)) -> 3
A53: 52 | B53: 116633 | C53: =_xlfn.NUMBERVALUE(MID(B53,2,1)) -> 1 | E53: SI EL CHI CUADRADO DA MAYOR QUE ESTE ULTIMO DATO, LOS DATOS DEL MOVIMIENTO SON
A54: 53 | B54: 450000 | C54: =_xlfn.NUMBERVALUE(MID(B54,2,1)) -> 5 | E54: CONFIABLES
A55: 54 | B55: 673178 | C55: =_xlfn.NUMBERVALUE(MID(B55,2,1)) -> 7
A56: 55 | B56: 12000 | C56: =_xlfn.NUMBERVALUE(MID(B56,2,1)) -> 2 | E56: ES DECIR | F56: 88.64 | G56: MAYOR QUE | H56: 15.5073 | I56: RESULTADO | J56: CONFIABLE
A57: 56 | B57: 27000 | C57: =_xlfn.NUMBERVALUE(MID(B57,2,1)) -> 7
A58: 57 | B58: 43740 | C58: =_xlfn.NUMBERVALUE(MID(B58,2,1)) -> 3
A59: 58 | B59: 15990 | C59: =_xlfn.NUMBERVALUE(MID(B59,2,1)) -> 5
A60: 59 | B60: 3777849 | C60: =_xlfn.NUMBERVALUE(MID(B60,2,1)) -> 7
A61: 60 | B61: 841508 | C61: =_xlfn.NUMBERVALUE(MID(B61,2,1)) -> 4
A62: 61 | B62: 31750 | C62: =_xlfn.NUMBERVALUE(MID(B62,2,1)) -> 1
A63: 62 | B63: 398615 | C63: =_xlfn.NUMBERVALUE(MID(B63,2,1)) -> 9
A64: 63 | B64: 1508000 | C64: =_xlfn.NUMBERVALUE(MID(B64,2,1)) -> 5
A65: 64 | B65: 160817 | C65: =_xlfn.NUMBERVALUE(MID(B65,2,1)) -> 6
A66: 65 | B66: 130100 | C66: =_xlfn.NUMBERVALUE(MID(B66,2,1)) -> 3
A67: 66 | B67: 229432 | C67: =_xlfn.NUMBERVALUE(MID(B67,2,1)) -> 2
A68: 67 | B68: 40000 | C68: =_xlfn.NUMBERVALUE(MID(B68,2,1)) -> 0
... A9657: 9656 | B9657: 366111 | C9657: =_xlfn.NUMBERVALUE(MID(B9657,2,1)) -> 6

Sheet PRIMEROS DOS DIGITOS
A1: REGISTRO | B1: VALOR | C1: VAMOS A EXTRAER LOS DOS PRIMEROS DIGITOS | J1: DESVIACION ABSOLUTA MEDIA (MAD) | P1: ESTA MAD LA COMPARAMOS CON LA TABLA PARA EL SEGUNDO DIGITO
A2: 1 | B2: 153800 | C2: =_xlfn.NUMBERVALUE(MID(B2,1,2)) -> 15 | I2: VALOR ABSOLUTO (FRECUENCIA OBSERVADA - FRECUENCIA ESPERADA)
A3: =+A2+1 -> 2 | B3: 9000 | C3: =_xlfn.NUMBERVALUE(MID(B3,1,2)) -> 90 | D3: VAMOS A VER LA FRECUENCIA EN QUE SE REPITE CADA NUMERO | I3: N = 90
A4: =+A3+1 -> 3 | B4: 37800 | C4: =_xlfn.NUMBERVALUE(MID(B4,1,2)) -> 37 | E4: ACUMULADA | F4: FRECUENCIA | G4: % OBSERVADO | H4: BENFORD DOS PRIMEROS DIGITOS | J4: VARIACION | K4: VALOR ABSOLUTO
A5: =+A4+1 -> 4 | B5: 100000 | C5: =_xlfn.NUMBERVALUE(MID(B5,1,2)) -> 10 | D5: 10 | E5: =FREQUENCY($C$2:$C$9657,D5) -> 453 | F5: =+E5 -> 453 | G5: =+F5/$F$96 -> 0.046913836 | H5: 0.041392685 | J5: =+(G5-H5) -> 0.0055211508 | K5: =ABS(J5) -> 0.0055211508
A6: =+A5+1 -> 5 | B6: 25000 | C6: =_xlfn.NUMBERVALUE(MID(B6,1,2)) -> 25 | D6: 11 | E6: =FREQUENCY($C$2:$C$9657,D6) -> 900 | F6: =+E6-F5 -> 447 | G6: =+F6/$F$96 -> 0.046292461 | H6: 0.037788561 | J6: =+(G6-H6) -> 0.0085038998 | K6: =ABS(J6) -> 0.0085038998
A7: =+A6+1 -> 6 | B7: 182900 | C7: =_xlfn.NUMBERVALUE(MID(B7,1,2)) -> 18 | D7: 12 | E7: =FREQUENCY($C$2:$C$9657,D7) -> 1262 | F7: =+E7-E6 -> 362 | G7: =+F7/$F$96 -> 0.037489644 | H7: 0.034762106 | J7: =+(G7-H7) -> 0.0027275375 | K7: =ABS(J7) -> 0.0027275375
A8: =+A7+1 -> 7 | B8: 157900 | C8: =_xlfn.NUMBERVALUE(MID(B8,1,2)) -> 15 | D8: 13 | E8: =FREQUENCY($C$2:$C$9657,D8) -> 1590 | F8: =+E8-E7 -> 328 | G8: =+F8/$F$96 -> 0.033968517 | H8: 0.032184683 | J8: =+(G8-H8) -> 0.0017838336 | K8: =ABS(J8) -> 0.0017838336
A9: =+A8+1 -> 8 | B9: 25000 | C9: =_xlfn.NUMBERVALUE(MID(B9,1,2)) -> 25 | D9: 14 | E9: =FREQUENCY($C$2:$C$9657,D9) -> 1923 | F9: =+E9-E8 -> 333 | G9: =+F9/$F$96 -> 0.03448633 | H9: 0.029963223 | J9: =+(G9-H9) -> 0.0045231064 | K9: =ABS(J9) -> 0.0045231064 | L9: MAD | M9: =+K96/90 -> 0.001845411 | N9: EN ESTE CASO NOS DA 0.001845411 QUE VIENDOLO EN LA TABA ES CONFORMIDAD MARGINALMENTE ACEPTABLE
A10: =+A9+1 -> 9 | B10: 181550 | C10: =_xlfn.NUMBERVALUE(MID(B10,1,2)) -> 18 | D10: 15 | E10: =FREQUENCY($C$2:$C$9657,D10) -> 2280 | F10: =+E10-E9 -> 357 | G10: =+F10/$F$96 -> 0.036971831 | H10: 0.028028724 | J10: =+(G10-H10) -> 0.0089431074 | K10: =ABS(J10) -> 0.0089431074
A11: =+A10+1 -> 10 | B11: 6000 | C11: =_xlfn.NUMBERVALUE(MID(B11,1,2)) -> 60 | D11: 16 | E11: =FREQUENCY($C$2:$C$9657,D11) -> 2559 | F11: =+E11-E10 -> 279 | G11: =+F11/$F$96 -> 0.028893952 | H11: 0.026328939 | J11: =+(G11-H11) -> 0.0025650132 | K11: =ABS(J11) -> 0.0025650132 | Q11: CHI CUADRADO Y CHI CUADRADO CRITICO
A12: =+A11+1 -> 11 | B12: 175550 | C12: =_xlfn.NUMBERVALUE(MID(B12,1,2)) -> 17 | D12: 17 | E12: =FREQUENCY($C$2:$C$9657,D12) -> 2814 | F12: =+E12-E11 -> 255 | G12: =+F12/$F$96 -> 0.026408451 | H12: 0.024823584 | J12: =+(G12-H12) -> 0.001584867 | K12: =ABS(J12) -> 0.001584867 | O12: SUMATORIA DE VALOR OBSERVADO MENOS VALOR ESPERADO ELEVADO AL CUADRADO
A13: =+A12+1 -> 12 | B13: 75500 | C13: =_xlfn.NUMBERVALUE(MID(B13,1,2)) -> 75 | D13: 18 | E13: =FREQUENCY($C$2:$C$9657,D13) -> 3092 | F13: =+E13-E12 -> 278 | G13: =+F13/$F$96 -> 0.028790389 | H13: 0.023481096 | J13: =+(G13-H13) -> 0.0053092935 | K13: =ABS(J13) -> 0.0053092935 | O13: VALOR ESPERADO
A14: =+A13+1 -> 13 | B14: 1000 | C14: =_xlfn.NUMBERVALUE(MID(B14,1,2)) -> 10 | D14: 19 | E14: =FREQUENCY($C$2:$C$9657,D14) -> 3321 | F14: =+E14-E13 -> 229 | G14: =+F14/$F$96 -> 0.023715824 | H14: 0.022276395 | J14: =+(G14-H14) -> 0.0014394296 | K14: =ABS(J14) -> 0.0014394296 | N14: VAMOS A VER LA FRECUENCIA EN QUE SE REPITE CADA NUMERO | T14: VALOR ESPERADO BENFORD = TOTAL DATOS POR % BENFORD
A15: =+A14+1 -> 14 | B15: 74500 | C15: =_xlfn.NUMBERVALUE(MID(B15,1,2)) -> 74 | D15: 20 | E15: =FREQUENCY($C$2:$C$9657,D15) -> 3594 | F15: =+E15-E14 -> 273 | G15: =+F15/$F$96 -> 0.028272577 | H15: 0.021189299 | J15: =+(G15-H15) -> 0.0070832776 | K15: =ABS(J15) -> 0.0070832776 | O15: ACUMULADA | P15: FRECUENCIA | Q15: % OBSERVADO | R15: BENFORD UN DIGITO | U15: VALOR OBSERVADO MENOS VALOR ESPERADO ELEVADO AL CUADRADO
A16: =+A15+1 -> 15 | B16: 184610 | C16: =_xlfn.NUMBERVALUE(MID(B16,1,2)) -> 18 | D16: 21 | E16: =FREQUENCY($C$2:$C$9657,D16) -> 3761 | F16: =+E16-E15 -> 167 | G16: =+F16/$F$96 -> 0.017294946 | H16: 0.020203386 | J16: =+(G16-H16) -> -0.0029084399 | K16: =ABS(J16) -> 0.0029084399 | N16: =+D5 -> 10 | O16: =FREQUENCY($C$2:$C$9657,N16) -> 453 | P16: =+O16 -> 453 | Q16: =+G5 -> 0.046913836 | R16: =+H5 -> 0.041392685 | T16: =+$P$107*R16 -> 399.68777 | U16: =+((P16-T16)^2)/T16 -> 7.111036
A17: =+A16+1 -> 16 | B17: 184610 | C17: =_xlfn.NUMBERVALUE(MID(B17,1,2)) -> 18 | D17: 22 | E17: =FREQUENCY($C$2:$C$9657,D17) -> 3945 | F17: =+E17-E16 -> 184 | G17: =+F17/$F$96 -> 0.01905551 | H17: 0.019305155 | J17: =+(G17-H17) -> -0.00024964567 | K17: =ABS(J17) -> 0.00024964567 | N17: =+D6 -> 11 | O17: =FREQUENCY($C$2:$C$9657,N17) -> 900 | P17: =+O17-O16 -> 447 | Q17: =+G6 -> 0.046292461 | R17: =+H6 -> 0.037788561 | T17: =+$P$107*R17 -> 364.88634 | U17: =+((P17-T17)^2)/T17 -> 18.478775 | V17: ESTE VALOR LO COMPARO CON 112.021986 QUE ES VALOR DEL CHI CUADRADO CRITICO PARA LOS DOS PRIMEROS DIGITOS
A18: =+A17+1 -> 17 | B18: 128000 | C18: =_xlfn.NUMBERVALUE(MID(B18,1,2)) -> 12 | D18: 23 | E18: =FREQUENCY($C$2:$C$9657,D18) -> 4099 | F18: =+E18-E17 -> 154 | G18: =+F18/$F$96 -> 0.015948633 | H18: 0.018483406 | J18: =+(G18-H18) -> -0.0025347727 | K18: =ABS(J18) -> 0.0025347727 | N18: =+D7 -> 12 | O18: =FREQUENCY($C$2:$C$9657,N18) -> 1262 | P18: =+O18-O17 -> 362 | Q18: =+G7 -> 0.037489644 | R18: =+H7 -> 0.034762106 | T18: =+$P$107*R18 -> 335.6629 | U18: =+((P18-T18)^2)/T18 -> 2.0664868 | V18: QUE SALE DE LA TABLA CHI CUADRADO CON UN 95% DE PROBABILIDAD Y ES FIJO
A19: =+A18+1 -> 18 | B19: 128000 | C19: =_xlfn.NUMBERVALUE(MID(B19,1,2)) -> 12 | D19: 24 | E19: =FREQUENCY($C$2:$C$9657,D19) -> 4293 | F19: =+E19-E18 -> 194 | G19: =+F19/$F$96 -> 0.020091135 | H19: 0.017728767 | J19: =+(G19-H19) -> 0.0023623681 | K19: =ABS(J19) -> 0.0023623681 | N19: =+D8 -> 13 | O19: =FREQUENCY($C$2:$C$9657,N19) -> 1590 | P19: =+O19-O18 -> 328 | Q19: =+G8 -> 0.033968517 | R19: =+H8 -> 0.032184683 | T19: =+$P$107*R19 -> 310.7753 | U19: =+((P19-T19)^2)/T19 -> 0.95467753
A20: =+A19+1 -> 19 | B20: 370370 | C20: =_xlfn.NUMBERVALUE(MID(B20,1,2)) -> 37 | D20: 25 | E20: =FREQUENCY($C$2:$C$9657,D20) -> 4459 | F20: =+E20-E19 -> 166 | G20: =+F20/$F$96 -> 0.017191384 | H20: 0.017033339 | J20: =+(G20-H20) -> 0.0001580443 | K20: =ABS(J20) -> 0.0001580443 | N20: =+D9 -> 14 | O20: =FREQUENCY($C$2:$C$9657,N20) -> 1923 | P20: =+O20-O19 -> 333 | Q20: =+G9 -> 0.03448633 | R20: =+H9 -> 0.029963223 | T20: =+$P$107*R20 -> 289.32488 | U20: =+((P20-T20)^2)/T20 -> 6.5929886
A21: =+A20+1 -> 20 | B21: 324485 | C21: =_xlfn.NUMBERVALUE(MID(B21,1,2)) -> 32 | D21: 26 | E21: =FREQUENCY($C$2:$C$9657,D21) -> 4612 | F21: =+E21-E20 -> 153 | G21: =+F21/$F$96 -> 0.01584507 | H21: 0.016390416 | J21: =+(G21-H21) -> -0.00054534577 | K21: =ABS(J21) -> 0.00054534577 | N21: =+D10 -> 15 | O21: =FREQUENCY($C$2:$C$9657,N21) -> 2280 | P21: =+O21-O20 -> 357 | Q21: =+G10 -> 0.036971831 | R21: =+H10 -> 0.028028724 | T21: =+$P$107*R21 -> 270.64536 | U21: =+((P21-T21)^2)/T21 -> 27.553123 | V21: SI EL CHI CUADRADO DA MAYOR QUE ESTE ULTIMO DATO, LOS DATOS DEL MOVIMIENTO SON
A22: =+A21+1 -> 21 | B22: 45885 | C22: =_xlfn.NUMBERVALUE(MID(B22,1,2)) -> 45 | D22: 27 | E22: =FREQUENCY($C$2:$C$9657,D22) -> 4777 | F22: =+E22-E21 -> 165 | G22: =+F22/$F$96 -> 0.017087821 | H22: 0.015794267 | J22: =+(G22-H22) -> 0.0012935539 | K22: =ABS(J22) -> 0.0012935539 | N22: =+D11 -> 16 | O22: =FREQUENCY($C$2:$C$9657,N22) -> 2559 | P22: =+O22-O21 -> 279 | Q22: =+G11 -> 0.028893952 | R22: =+H11 -> 0.026328939 | T22: =+$P$107*R22 -> 254.23223 | U22: =+((P22-T22)^2)/T22 -> 2.4129211 | V22: CONFIABLES
A23: =+A22+1 -> 22 | B23: 352295 | C23: =_xlfn.NUMBERVALUE(MID(B23,1,2)) -> 35 | D23: 28 | E23: =FREQUENCY($C$2:$C$9657,D23) -> 4908 | F23: =+E23-E22 -> 131 | G23: =+F23/$F$96 -> 0.013566694 | H23: 0.015239967 | J23: =+(G23-H23) -> -0.0016732723 | K23: =ABS(J23) -> 0.0016732723 | N23: =+D12 -> 17 | O23: =FREQUENCY($C$2:$C$9657,N23) -> 2814 | P23: =+O23-O22 -> 255 | Q23: =+G12 -> 0.026408451 | R23: =+H12 -> 0.024823584 | T23: =+$P$107*R23 -> 239.69652 | U23: =+((P23-T23)^2)/T23 -> 0.97705365
A24: =+A23+1 -> 23 | B24: 335095 | C24: =_xlfn.NUMBERVALUE(MID(B24,1,2)) -> 33 | D24: 29 | E24: =FREQUENCY($C$2:$C$9657,D24) -> 5073 | F24: =+E24-E23 -> 165 | G24: =+F24/$F$96 -> 0.017087821 | H24: 0.014723257 | J24: =+(G24-H24) -> 0.0023645642 | K24: =ABS(J24) -> 0.0023645642 | N24: =+D13 -> 18 | O24: =FREQUENCY($C$2:$C$9657,N24) -> 3092 | P24: =+O24-O23 -> 278 | Q24: =+G13 -> 0.028790389 | R24: =+H13 -> 0.023481096 | T24: =+$P$107*R24 -> 226.73346 | U24: =+((P24-T24)^2)/T24 -> 11.59184 | V24: ES DECIR | W24: =+U107 -> 439.65133 | X24: MAYOR QUE | Y24: 112.02199 | Z24: RESULTADO | AA24: CONFIABLE
A25: =+A24+1 -> 24 | B25: 1800 | C25: =_xlfn.NUMBERVALUE(MID(B25,1,2)) -> 18 | D25: 30 | E25: =FREQUENCY($C$2:$C$9657,D25) -> 5235 | F25: =+E25-E24 -> 162 | G25: =+F25/$F$96 -> 0.016777133 | H25: 0.014240439 | J25: =+(G25-H25) -> 0.0025366943 | K25: =ABS(J25) -> 0.0025366943 | N25: =+D14 -> 19 | O25: =FREQUENCY($C$2:$C$9657,N25) -> 3321 | P25: =+O25-O24 -> 229 | Q25: =+G14 -> 0.023715824 | R25: =+H14 -> 0.022276395 | T25: =+$P$107*R25 -> 215.10087 | U25: =+((P25-T25)^2)/T25 -> 0.89811767
A26: =+A25+1 -> 25 | B26: 7000 | C26: =_xlfn.NUMBERVALUE(MID(B26,1,2)) -> 70 | D26: 31 | E26: =FREQUENCY($C$2:$C$9657,D26) -> 5364 | F26: =+E26-E25 -> 129 | G26: =+F26/$F$96 -> 0.013359569 | H26: 0.013788284 | J26: =+(G26-H26) -> -0.00042871531 | K26: =ABS(J26) -> 0.00042871531 | N26: =+D15 -> 20 | O26: =FREQUENCY($C$2:$C$9657,N26) -> 3594 | P26: =+O26-O25 -> 273 | Q26: =+G15 -> 0.028272577 | R26: =+H15 -> 0.021189299 | T26: =+$P$107*R26 -> 204.60387 | U26: =+((P26-T26)^2)/T26 -> 22.863841
A27: =+A26+1 -> 26 | B27: 8375 | C27: =_xlfn.NUMBERVALUE(MID(B27,1,2)) -> 83 | D27: 32 | E27: =FREQUENCY($C$2:$C$9657,D27) -> 5495 | F27: =+E27-E26 -> 131 | G27: =+F27/$F$96 -> 0.013566694 | H27: 0.013363962 | J27: =+(G27-H27) -> 0.00020273273 | K27: =ABS(J27) -> 0.00020273273 | N27: =+D16 -> 21 | O27: =FREQUENCY($C$2:$C$9657,N27) -> 3761 | P27: =+O27-O26 -> 167 | Q27: =+G16 -> 0.017294946 | R27: =+H16 -> 0.020203386 | T27: =+$P$107*R27 -> 195.0839 | U27: =+((P27-T27)^2)/T27 -> 4.0429027
A28: =+A27+1 -> 27 | B28: 25 | C28: =_xlfn.NUMBERVALUE(MID(B28,1,2)) -> 25 | D28: 33 | E28: =FREQUENCY($C$2:$C$9657,D28) -> 5608 | F28: =+E28-E27 -> 113 | G28: =+F28/$F$96 -> 0.011702568 | H28: 0.012964977 | J28: =+(G28-H28) -> -0.0012624088 | K28: =ABS(J28) -> 0.0012624088 | N28: =+D17 -> 22 | O28: =FREQUENCY($C$2:$C$9657,N28) -> 3945 | P28: =+O28-O27 -> 184 | Q28: =+G17 -> 0.01905551 | R28: =+H17 -> 0.019305155 | T28: =+$P$107*R28 -> 186.41058 | U28: =+((P28-T28)^2)/T28 -> 0.031172528
A29: =+A28+1 -> 28 | B29: 182350 | C29: =_xlfn.NUMBERVALUE(MID(B29,1,2)) -> 18 | D29: 34 | E29: =FREQUENCY($C$2:$C$9657,D29) -> 5713 | F29: =+E29-E28 -> 105 | G29: =+F29/$F$96 -> 0.010874068 | H29: 0.012589127 | J29: =+(G29-H29) -> -0.0017150594 | K29: =ABS(J29) -> 0.0017150594 | N29: =+D18 -> 23 | O29: =FREQUENCY($C$2:$C$9657,N29) -> 4099 | P29: =+O29-O28 -> 154 | Q29: =+G18 -> 0.015948633 | R29: =+H18 -> 0.018483406 | T29: =+$P$107*R29 -> 178.47577 | U29: =+((P29-T29)^2)/T29 -> 3.3565515
A30: =+A29+1 -> 29 | B30: 157350 | C30: =_xlfn.NUMBERVALUE(MID(B30,1,2)) -> 15 | D30: 35 | E30: =FREQUENCY($C$2:$C$9657,D30) -> 5843 | F30: =+E30-E29 -> 130 | G30: =+F30/$F$96 -> 0.013463132 | H30: 0.012234456 | J30: =+(G30-H30) -> 0.0012286753 | K30: =ABS(J30) -> 0.0012286753 | N30: =+D19 -> 24 | O30: =FREQUENCY($C$2:$C$9657,N30) -> 4293 | P30: =+O30-O29 -> 194 | Q30: =+G19 -> 0.020091135 | R30: =+H19 -> 0.017728767 | T30: =+$P$107*R30 -> 171.18897 | U30: =+((P30-T30)^2)/T30 -> 3.039582
A31: =+A30+1 -> 30 | B31: 25000 | C31: =_xlfn.NUMBERVALUE(MID(B31,1,2)) -> 25 | D31: 36 | E31: =FREQUENCY($C$2:$C$9657,D31) -> 5958 | F31: =+E31-E30 -> 115 | G31: =+F31/$F$96 -> 0.011909693 | H31: 0.011899223 | J31: =+(G31-H31) -> 1.0470155e-05 | K31: =ABS(J31) -> 1.0470155e-05 | N31: =+D20 -> 25 | O31: =FREQUENCY($C$2:$C$9657,N31) -> 4459 | P31: =+O31-O30 -> 166 | Q31: =+G20 -> 0.017191384 | R31: =+H20 -> 0.017033339 | T31: =+$P$107*R31 -> 164.47392 | U31: =+((P31-T31)^2)/T31 -> 0.014159735
A32: =+A31+1 -> 31 | B32: 126600 | C32: =_xlfn.NUMBERVALUE(MID(B32,1,2)) -> 12 | D32: 37 | E32: =FREQUENCY($C$2:$C$9657,D32) -> 6042 | F32: =+E32-E31 -> 84 | G32: =+F32/$F$96 -> 0.0086992543 | H32: 0.011581873 | J32: =+(G32-H32) -> -0.0028826182 | K32: =ABS(J32) -> 0.0028826182 | N32: =+D21 -> 26 | O32: =FREQUENCY($C$2:$C$9657,N32) -> 4612 | P32: =+O32-O31 -> 153 | Q32: =+G21 -> 0.01584507 | R32: =+H21 -> 0.016390416 | T32: =+$P$107*R32 -> 158.26586 | U32: =+((P32-T32)^2)/T32 -> 0.17520688
A33: =+A32+1 -> 32 | B33: 101600 | C33: =_xlfn.NUMBERVALUE(MID(B33,1,2)) -> 10 | D33: 38 | E33: =FREQUENCY($C$2:$C$9657,D33) -> 6148 | F33: =+E33-E32 -> 106 | G33: =+F33/$F$96 -> 0.01097763 | H33: 0.01128101 | J33: =+(G33-H33) -> -0.00030337992 | K33: =ABS(J33) -> 0.00030337992 | N33: =+D22 -> 27 | O33: =FREQUENCY($C$2:$C$9657,N33) -> 4777 | P33: =+O33-O32 -> 165 | Q33: =+G22 -> 0.017087821 | R33: =+H22 -> 0.015794267 | T33: =+$P$107*R33 -> 152.50944 | U33: =+((P33-T33)^2)/T33 -> 1.0229792
A34: =+A33+1 -> 33 | B34: 25000 | C34: =_xlfn.NUMBERVALUE(MID(B34,1,2)) -> 25 | D34: 39 | E34: =FREQUENCY($C$2:$C$9657,D34) -> 6242 | F34: =+E34-E33 -> 94 | G34: =+F34/$F$96 -> 0.0097348799 | H34: 0.010995384 | J34: =+(G34-H34) -> -0.0012605044 | K34: =ABS(J34) -> 0.0012605044 | N34: =+D23 -> 28 | O34: =FREQUENCY($C$2:$C$9657,N34) -> 4908 | P34: =+O34-O33 -> 131 | Q34: =+G23 -> 0.013566694 | R34: =+H23 -> 0.015239967 | T34: =+$P$107*R34 -> 147.15712 | U34: =+((P34-T34)^2)/T34 -> 1.7739708
A35: =+A34+1 -> 34 | B35: 153300 | C35: =_xlfn.NUMBERVALUE(MID(B35,1,2)) -> 15 | D35: 40 | E35: =FREQUENCY($C$2:$C$9657,D35) -> 6355 | F35: =+E35-E34 -> 113 | G35: =+F35/$F$96 -> 0.011702568 | H35: 0.010723865 | J35: =+(G35-H35) -> 0.00097870296 | K35: =ABS(J35) -> 0.00097870296 | N35: =+D24 -> 29 | O35: =FREQUENCY($C$2:$C$9657,N35) -> 5073 | P35: =+O35-O34 -> 165 | Q35: =+G24 -> 0.017087821 | R35: =+H24 -> 0.014723257 | T35: =+$P$107*R35 -> 142.16777 | U35: =+((P35-T35)^2)/T35 -> 3.6668707
A36: =+A35+1 -> 35 | B36: 153300 | C36: =_xlfn.NUMBERVALUE(MID(B36,1,2)) -> 15 | D36: 41 | E36: =FREQUENCY($C$2:$C$9657,D36) -> 6420 | F36: =+E36-E35 -> 65 | G36: =+F36/$F$96 -> 0.0067315659 | H36: 0.010465434 | J36: =+(G36-H36) -> -0.0037338678 | K36: =ABS(J36) -> 0.0037338678 | N36: =+D25 -> 30 | O36: =FREQUENCY($C$2:$C$9657,N36) -> 5235 | P36: =+O36-O35 -> 162 | Q36: =+G25 -> 0.016777133 | R36: =+H25 -> 0.014240439 | T36: =+$P$107*R36 -> 137.50568 | U36: =+((P36-T36)^2)/T36 -> 4.3632504
... A94: =+A93+1 -> 93 | B94: 59974 | C94: =_xlfn.NUMBERVALUE(MID(B94,1,2)) -> 59 | D94: 99 | E94: =FREQUENCY($C$2:$C$9657,D94) -> 9656 | F94: =+E94-E93 -> 22 | G94: =+F94/$F$96 -> 0.0022783761 | H94: 0.0043648054 | J94: =+(G94-H94) -> -0.0020864293 | K94: =ABS(J94) -> 0.0020864293 | N94: =+D83 -> 88 | O94: =FREQUENCY($C$2:$C$9657,N94) -> 9210 | P94: =+O94-O93 -> 49 | Q94: =+G83 -> 0.005074565 | R94: =+H83 -> 0.0049073345 | T94: =+$P$107*R94 -> 47.385222 | U94: =+((P94-T94)^2)/T94 -> 0.055027881
A95: =+A94+1 -> 94 | B95: 299700 | C95: =_xlfn.NUMBERVALUE(MID(B95,1,2)) -> 29 | N95: =+D84 -> 89 | O95: =FREQUENCY($C$2:$C$9657,N95) -> 9259 | P95: =+O95-O94 -> 49 | Q95: =+G84 -> 0.005074565 | R95: =+H84 -> 0.0048525028 | T95: =+$P$107*R95 -> 46.855767 | U95: =+((P95-T95)^2)/T95 -> 0.09812528
A96: =+A95+1 -> 95 | B96: 54875 | C96: =_xlfn.NUMBERVALUE(MID(B96,1,2)) -> 54 | E96: TOTAL | F96: =SUM(F5:F95) -> 9656 | G96: =SUM(G5:G94) -> 1 | H96: =SUM(H5:H94) -> 1 | J96: =SUM(J5:J95) -> 0 | K96: =SUM(K5:K95) -> 0.16608699 | N96: =+D85 -> 90 | O96: =FREQUENCY($C$2:$C$9657,N96) -> 9300 | P96: =+O96-O95 -> 41 | Q96: =+G85 -> 0.0042460646 | R96: =+H85 -> 0.0047988829 | T96: =+$P$107*R96 -> 46.338013 | U96: =+((P96-T96)^2)/T96 -> 0.61492459
A97: =+A96+1 -> 96 | B97: 12000 | C97: =_xlfn.NUMBERVALUE(MID(B97,1,2)) -> 12 | N97: =+D86 -> 91 | O97: =FREQUENCY($C$2:$C$9657,N97) -> 9327 | P97: =+O97-O96 -> 27 | Q97: =+G86 -> 0.0027961889 | R97: =+H86 -> 0.004746435 | T97: =+$P$107*R97 -> 45.831577 | U97: =+((P97-T97)^2)/T97 -> 7.7376408
A98: =+A97+1 -> 97 | B98: 15000 | C98: =_xlfn.NUMBERVALUE(MID(B98,1,2)) -> 15 | N98: =+D87 -> 92 | O98: =FREQUENCY($C$2:$C$9657,N98) -> 9365 | P98: =+O98-O97 -> 38 | Q98: =+G87 -> 0.003935377 | R98: =+H87 -> 0.0046951212 | T98: =+$P$107*R98 -> 45.33609 | U98: =+((P98-T98)^2)/T98 -> 1.1870945
A99: =+A98+1 -> 98 | B99: 14132 | C99: =_xlfn.NUMBERVALUE(MID(B99,1,2)) -> 14 | N99: =+D88 -> 93 | O99: =FREQUENCY($C$2:$C$9657,N99) -> 9440 | P99: =+O99-O98 -> 75 | Q99: =+G88 -> 0.0077671914 | R99: =+H88 -> 0.004644905 | T99: =+$P$107*R99 -> 44.851203 | U99: =+((P99-T99)^2)/T99 -> 20.265899
A100: =+A99+1 -> 99 | B100: 24001 | C100: =_xlfn.NUMBERVALUE(MID(B100,1,2)) -> 24 | N100: =+D89 -> 94 | O100: =FREQUENCY($C$2:$C$9657,N100) -> 9485 | P100: =+O100-O99 -> 45 | Q100: =+G89 -> 0.0046603148 | R100: =+H89 -> 0.0045957517 | T100: =+$P$107*R100 -> 44.376578 | U100: =+((P100-T100)^2)/T100 -> 0.0087581021
A101: =+A100+1 -> 100 | B101: 7688 | C101: =_xlfn.NUMBERVALUE(MID(B101,1,2)) -> 76 | N101: =+D90 -> 95 | O101: =FREQUENCY($C$2:$C$9657,N101) -> 9520 | P101: =+O101-O100 -> 35 | Q101: =+G90 -> 0.0036246893 | R101: =+H90 -> 0.0045476278 | T101: =+$P$107*R101 -> 43.911894 | U101: =+((P101-T101)^2)/T101 -> 1.8086637
A102: =+A101+1 -> 101 | B102: 2020630 | C102: =_xlfn.NUMBERVALUE(MID(B102,1,2)) -> 20 | N102: =+D91 -> 96 | O102: =FREQUENCY($C$2:$C$9657,N102) -> 9549 | P102: =+O102-O101 -> 29 | Q102: =+G91 -> 0.003003314 | R102: =+H91 -> 0.0045005012 | T102: =+$P$107*R102 -> 43.45684 | U102: =+((P102-T102)^2)/T102 -> 4.8093745
A103: =+A102+1 -> 102 | B103: 130450 | C103: =_xlfn.NUMBERVALUE(MID(B103,1,2)) -> 13 | N103: =+D92 -> 97 | O103: =FREQUENCY($C$2:$C$9657,N103) -> 9591 | P103: =+O103-O102 -> 42 | Q103: =+G92 -> 0.0043496272 | R103: =+H92 -> 0.0044543414 | T103: =+$P$107*R103 -> 43.011121 | U103: =+((P103-T103)^2)/T103 -> 0.02376979
A104: =+A103+1 -> 103 | B104: 233750 | C104: =_xlfn.NUMBERVALUE(MID(B104,1,2)) -> 23 | N104: =+D93 -> 98 | O104: =FREQUENCY($C$2:$C$9657,N104) -> 9634 | P104: =+O104-O103 -> 43 | Q104: =+G93 -> 0.0044531897 | R104: =+H93 -> 0.0044091189 | T104: =+$P$107*R104 -> 42.574452 | U104: =+((P104-T104)^2)/T104 -> 0.0042535127
A105: =+A104+1 -> 104 | B105: 126121 | C105: =_xlfn.NUMBERVALUE(MID(B105,1,2)) -> 12 | N105: =+D94 -> 99 | O105: =FREQUENCY($C$2:$C$9657,N105) -> 9656 | P105: =+O105-O104 -> 22 | Q105: =+G94 -> 0.0022783761 | R105: =+H94 -> 0.0043648054 | T105: =+$P$107*R105 -> 42.146561 | U105: =+((P105-T105)^2)/T105 -> 9.6302975
A106: =+A105+1 -> 105 | B106: 124350 | C106: =_xlfn.NUMBERVALUE(MID(B106,1,2)) -> 12
A107: =+A106+1 -> 106 | B107: 300000 | C107: =_xlfn.NUMBERVALUE(MID(B107,1,2)) -> 30 | O107: TOTAL | P107: =SUM(P16:P106) -> 9656 | Q107: =SUM(Q16:Q106) -> 1 | R107: =SUM(R16:R106) -> 1 | T107: =SUM(T16:T106) -> 9656 | U107: =SUM(U16:U106) -> 439.65133
A108: =+A107+1 -> 107 | B108: 857000 | C108: =_xlfn.NUMBERVALUE(MID(B108,1,2)) -> 85
A109: =+A108+1 -> 108 | B109: 84359 | C109: =_xlfn.NUMBERVALUE(MID(B109,1,2)) -> 84
A110: =+A109+1 -> 109 | B110: 18000 | C110: =_xlfn.NUMBERVALUE(MID(B110,1,2)) -> 18
A111: =+A110+1 -> 110 | B111: 12000 | C111: =_xlfn.NUMBERVALUE(MID(B111,1,2)) -> 12
A112: =+A111+1 -> 111 | B112: 52600 | C112: =_xlfn.NUMBERVALUE(MID(B112,1,2)) -> 52
A113: =+A112+1 -> 112 | B113: 45000 | C113: =_xlfn.NUMBERVALUE(MID(B113,1,2)) -> 45
A114: =+A113+1 -> 113 | B114: 17000 | C114: =_xlfn.NUMBERVALUE(MID(B114,1,2)) -> 17
A115: =+A114+1 -> 114 | B115: 16000 | C115: =_xlfn.NUMBERVALUE(MID(B115,1,2)) -> 16
A116: =+A115+1 -> 115 | B116: 1000 | C116: =_xlfn.NUMBERVALUE(MID(B116,1,2)) -> 10
A117: =+A116+1 -> 116 | B117: 3000 | C117: =_xlfn.NUMBERVALUE(MID(B117,1,2)) -> 30
A118: =+A117+1 -> 117 | B118: 2512642 | C118: =_xlfn.NUMBERVALUE(MID(B118,1,2)) -> 25
A119: =+A118+1 -> 118 | B119: 81945 | C119: =_xlfn.NUMBERVALUE(MID(B119,1,2)) -> 81
... A9657: =+A9656+1 -> 9656 | B9657: 366111 | C9657: =_xlfn.NUMBERVALUE(MID(B9657,1,2)) -> 36

Sheet GRAFICA  PRIMER DIGITO
A2: NUMERO | B2: OBSERVADO | C2: BENFORD
A3: 1 | B3: =+'PRIMER DIGITO'!G5 -> 0.34351698 | C3: =+'PRIMER DIGITO'!H5 -> 0.30103
A4: 2 | B4: =+'PRIMER DIGITO'!G6 -> 0.18144159 | C4: =+'PRIMER DIGITO'!H6 -> 0.17609126
A5: 3 | B5: =+'PRIMER DIGITO'!G7 -> 0.12127175 | C5: =+'PRIMER DIGITO'!H7 -> 0.12493874
A6: 4 | B6: =+'PRIMER DIGITO'!G8 -> 0.085024855 | C6: =+'PRIMER DIGITO'!H8 -> 0.096910013
A7: 5 | B7: =+'PRIMER DIGITO'!G9 -> 0.0754971 | C7: =+'PRIMER DIGITO'!H9 -> 0.079181246
A8: 6 | B8: =+'PRIMER DIGITO'!G10 -> 0.053852527 | C8: =+'PRIMER DIGITO'!H10 -> 0.06694679
A9: 7 | B9: =+'PRIMER DIGITO'!G11 -> 0.051574151 | C9: =+'PRIMER DIGITO'!H11 -> 0.057991947
A10: 8 | B10: =+'PRIMER DIGITO'!G12 -> 0.046706711 | C10: =+'PRIMER DIGITO'!H12 -> 0.051152522
A11: 9 | B11: =+'PRIMER DIGITO'!G13 -> 0.041114333 | C11: =+'PRIMER DIGITO'!H13 -> 0.045757491

Sheet GRAFICA SEGUNDO DIGITO
A2: NUMERO | B2: OBSERVADO | C2: BENFORD
A3: 0 | B3: =+'SEGUNDO DIGITO'!G35 -> #VALUE! | C3: =+'SEGUNDO DIGITO'!H35 -> 0.11967927
A4: 1 | B4: =+'SEGUNDO DIGITO'!G36 -> #VALUE! | C4: =+'SEGUNDO DIGITO'!H36 -> 0.1138901
A5: 2 | B5: =+'SEGUNDO DIGITO'!G37 -> #VALUE! | C5: =+'SEGUNDO DIGITO'!H37 -> 0.1088215
A6: 3 | B6: =+'SEGUNDO DIGITO'!G38 -> #VALUE! | C6: =+'SEGUNDO DIGITO'!H38 -> 0.10432956
A7: 4 | B7: =+'SEGUNDO DIGITO'!G39 -> #VALUE! | C7: =+'SEGUNDO DIGITO'!H39 -> 0.1003082
A8: 5 | B8: =+'SEGUNDO DIGITO'!G40 -> #VALUE! | C8: =+'SEGUNDO DIGITO'!H40 -> 0.096677236
A9: 6 | B9: =+'SEGUNDO DIGITO'!G41 -> #VALUE! | C9: =+'SEGUNDO DIGITO'!H41 -> 0.093374736
A10: 7 | B10: =+'SEGUNDO DIGITO'!G42 -> #VALUE! | C10: =+'SEGUNDO DIGITO'!H42 -> 0.090351989
A11: 8 | B11: =+'SEGUNDO DIGITO'!G43 -> #VALUE! | C11: =+'SEGUNDO DIGITO'!H43 -> 0.087570054
A12: 9 | B12: =+'SEGUNDO DIGITO'!G44 -> #VALUE! | C12: =+'SEGUNDO DIGITO'!H44 -> 0.084997352

Sheet GRAFICA DOS PRIMEROS
A2: NUMERO | B2: OBSERVADO | C2: BENFORD
A3: 10 | B3: =+'PRIMEROS DOS DIGITOS'!G5 -> 0.046913836 | C3: =+'PRIMEROS DOS DIGITOS'!H5 -> 0.041392685
A4: 11 | B4: =+'PRIMEROS DOS DIGITOS'!G6 -> 0.046292461 | C4: =+'PRIMEROS DOS DIGITOS'!H6 -> 0.037788561
A5: 12 | B5: =+'PRIMEROS DOS DIGITOS'!G7 -> 0.037489644 | C5: =+'PRIMEROS DOS DIGITOS'!H7 -> 0.034762106
A6: 13 | B6: =+'PRIMEROS DOS DIGITOS'!G8 -> 0.033968517 | C6: =+'PRIMEROS DOS DIGITOS'!H8 -> 0.032184683
A7: 14 | B7: =+'PRIMEROS DOS DIGITOS'!G9 -> 0.03448633 | C7: =+'PRIMEROS DOS DIGITOS'!H9 -> 0.029963223
A8: 15 | B8: =+'PRIMEROS DOS DIGITOS'!G10 -> 0.036971831 | C8: =+'PRIMEROS DOS DIGITOS'!H10 -> 0.028028724
A9: 16 | B9: =+'PRIMEROS DOS DIGITOS'!G11 -> 0.028893952 | C9: =+'PRIMEROS DOS DIGITOS'!H11 -> 0.026328939
A10: 17 | B10: =+'PRIMEROS DOS DIGITOS'!G12 -> 0.026408451 | C10: =+'PRIMEROS DOS DIGITOS'!H12 -> 0.024823584
A11: 18 | B11: =+'PRIMEROS DOS DIGITOS'!G13 -> 0.028790389 | C11: =+'PRIMEROS DOS DIGITOS'!H13 -> 0.023481096
A12: 19 | B12: =+'PRIMEROS DOS DIGITOS'!G14 -> 0.023715824 | C12: =+'PRIMEROS DOS DIGITOS'!H14 -> 0.022276395
A13: 20 | B13: =+'PRIMEROS DOS DIGITOS'!G15 -> 0.028272577 | C13: =+'PRIMEROS DOS DIGITOS'!H15 -> 0.021189299
A14: 21 | B14: =+'PRIMEROS DOS DIGITOS'!G16 -> 0.017294946 | C14: =+'PRIMEROS DOS DIGITOS'!H16 -> 0.020203386
... A92: 99 | B92: =+'PRIMEROS DOS DIGITOS'!G94 -> 0.0022783761 | C92: =+'PRIMEROS DOS DIGITOS'!H94 -> 0.0043648054
